{"tgs":1,"v":"5.5.2","fr":30,"ip":0,"op":1,"w":512,"h":512,"nm":"Comp 1","ddd":0,"assets":[],"layers":[{"ddd":0,"ind":1,"ty":4,"nm":"Слой 39","sr":1,"ks":{"p":{"a":0,"k":[247.31,140.096,0]}},"ao":0,"shapes":[{"ty":"gr","it":[{"ind":0,"ty":"sh","ks":{"a":0,"k":{"i":[[0,0],[0,0],[30.961,0],[16.582,-10.13],[0,0]],"o":[[0,0],[-16.582,-10.13],[-30.961,0],[0,0],[0,0]],"v":[[75.945,77.998],[69.948,-59.008],[0,-77.998],[-69.948,-59.008],[-75.945,77.998]],"c":false}},"nm":"Path 1","hd":false},{"ty":"st","c":{"a":0,"k":[0.419607847929,0.082352943718,0.082352943718,1]},"o":{"a":0,"k":100},"w":{"a":0,"k":8},"lc":2,"lj":2,"bm":0,"nm":"Stroke 1","hd":false},{"ty":"tr","p":{"a":0,"k":[0,0]},"a":{"a":0,"k":[0,0]},"s":{"a":0,"k":[100,100]},"r":{"a":0,"k":0},"o":{"a":0,"k":100},"sk":{"a":0,"k":0},"sa":{"a":0,"k":0},"nm":"Transform"}],"nm":"Group 1","bm":0,"hd":false}],"ip":0,"op":1,"st":0,"bm":0},{"ddd":0,"ind":2,"ty":4,"nm":"Слой 38","sr":1,"ks":{"p":{"a":0,"k":[427.67,248.533,0]}},"ao":0,"shapes":[{"ty":"gr","it":[{"ind":0,"ty":"sh","ks":{"a":0,"k":{"i":[[0,0],[0,0]],"o":[[0,0],[0,0]],"v":[[7.575,6.694],[-7.575,-6.694]],"c":false}},"nm":"Path 1","hd":false},{"ty":"st","c":{"a":0,"k":[0.529411792755,0.058823529631,0.058823529631,1]},"o":{"a":0,"k":100},"w":{"a":0,"k":8},"lc":2,"lj":2,"bm":0,"nm":"Stroke 1","hd":false},{"ty":"tr","p":{"a":0,"k":[0,0]},"a":{"a":0,"k":[0,0]},"s":{"a":0,"k":[100,100]},"r":{"a":0,"k":0},"o":{"a":0,"k":100},"sk":{"a":0,"k":0},"sa":{"a":0,"k":0},"nm":"Transform"}],"nm":"Group 1","bm":0,"hd":false}],"ip":0,"op":1,"st":0,"bm":0},{"ddd":0,"ind":3,"ty":4,"nm":"Слой 37","sr":1,"ks":{"p":{"a":0,"k":[427.67,269.456,0]}},"ao":0,"shapes":[{"ty":"gr","it":[{"ind":0,"ty":"sh","ks":{"a":0,"k":{"i":[[0,0],[0,0],[0,0]],"o":[[0,0],[0,0],[0,0]],"v":[[7.575,27.617],[7.575,-14.228],[-7.575,-27.617]],"c":false}},"nm":"Path 1","hd":false},{"ty":"st","c":{"a":0,"k":[0.266666680574,0.023529412225,0.023529412225,1]},"o":{"a":0,"k":100},"w":{"a":0,"k":8},"lc":2,"lj":2,"bm":0,"nm":"Stroke 1","hd":false},{"ty":"tr","p":{"a":0,"k":[0,0]},"a":{"a":0,"k":[0,0]},"s":{"a":0,"k":[100,100]},"r":{"a":0,"k":0},"o":{"a":0,"k":100},"sk":{"a":0,"k":0},"sa":{"a":0,"k":0},"nm":"Transform"}],"nm":"Group 1","bm":0,"hd":false}],"ip":0,"op":1,"st":0,"bm":0},{"ddd":0,"ind":4,"ty":4,"nm":"Слой 36","sr":1,"ks":{"p":{"a":0,"k":[426.638,269.456,0]}},"ao":0,"shapes":[{"ty":"gr","it":[{"ind":0,"ty":"sh","ks":{"a":0,"k":{"i":[[0,0],[0,0],[0,0],[0,0],[0,0],[0,0]],"o":[[0,0],[0,0],[0,0],[0,0],[0,0],[0,0]],"v":[[-8.607,17.908],[6.301,27.617],[8.607,27.617],[8.607,-14.228],[-6.542,-27.617],[-8.607,-27.617]],"c":true}},"nm":"Path 1","hd":false},{"ty":"gf","o":{"a":0,"k":100},"r":1,"bm":0,"g":{"p":3,"k":{"a":0,"k":[0,0.925,0.133,0.114,0.5,0.884,0.129,0.11,1,0.843,0.125,0.106]}},"s":{"a":0,"k":[5.362,-0.455]},"e":{"a":0,"k":[-7.061,-0.455]},"t":1,"nm":"Gradient_iq28vHZXcX","hd":false},{"ty":"tr","p":{"a":0,"k":[0,0]},"a":{"a":0,"k":[0,0]},"s":{"a":0,"k":[100,100]},"r":{"a":0,"k":0},"o":{"a":0,"k":100},"sk":{"a":0,"k":0},"sa":{"a":0,"k":0},"nm":"Transform"}],"nm":"Group 1","bm":0,"hd":false}],"ip":0,"op":1,"st":0,"bm":0},{"ddd":0,"ind":5,"ty":4,"nm":"Слой 35","sr":1,"ks":{"p":{"a":0,"k":[68.309,248.533,0]}},"ao":0,"shapes":[{"ty":"gr","it":[{"ind":0,"ty":"sh","ks":{"a":0,"k":{"i":[[0,0],[0,0]],"o":[[0,0],[0,0]],"v":[[-7.575,6.694],[7.575,-6.694]],"c":false}},"nm":"Path 1","hd":false},{"ty":"st","c":{"a":0,"k":[0.65098041296,0.0941176489,0.082352943718,1]},"o":{"a":0,"k":100},"w":{"a":0,"k":8},"lc":2,"lj":1,"ml":10,"bm":0,"nm":"Stroke 1","hd":false},{"ty":"tr","p":{"a":0,"k":[0,0]},"a":{"a":0,"k":[0,0]},"s":{"a":0,"k":[100,100]},"r":{"a":0,"k":0},"o":{"a":0,"k":100},"sk":{"a":0,"k":0},"sa":{"a":0,"k":0},"nm":"Transform"}],"nm":"Group 1","bm":0,"hd":false}],"ip":0,"op":1,"st":0,"bm":0},{"ddd":0,"ind":6,"ty":4,"nm":"Слой 34","sr":1,"ks":{"p":{"a":0,"k":[68.309,269.456,0]}},"ao":0,"shapes":[{"ty":"gr","it":[{"ind":0,"ty":"sh","ks":{"a":0,"k":{"i":[[0,0],[0,0],[0,0]],"o":[[0,0],[0,0],[0,0]],"v":[[-7.575,27.617],[-7.575,-14.228],[7.575,-27.617]],"c":false}},"nm":"Path 1","hd":false},{"ty":"st","c":{"a":0,"k":[0.266666680574,0.023529412225,0.023529412225,1]},"o":{"a":0,"k":100},"w":{"a":0,"k":8},"lc":2,"lj":2,"bm":0,"nm":"Stroke 1","hd":false},{"ty":"tr","p":{"a":0,"k":[0,0]},"a":{"a":0,"k":[0,0]},"s":{"a":0,"k":[100,100]},"r":{"a":0,"k":0},"o":{"a":0,"k":100},"sk":{"a":0,"k":0},"sa":{"a":0,"k":0},"nm":"Transform"}],"nm":"Group 1","bm":0,"hd":false}],"ip":0,"op":1,"st":0,"bm":0},{"ddd":0,"ind":7,"ty":4,"nm":"Слой 33","sr":1,"ks":{"p":{"a":0,"k":[69.342,269.456,0]}},"ao":0,"shapes":[{"ty":"gr","it":[{"ind":0,"ty":"sh","ks":{"a":0,"k":{"i":[[0,0],[0,0],[0,0],[0,0],[0,0],[0,0]],"o":[[0,0],[0,0],[0,0],[0,0],[0,0],[0,0]],"v":[[7.607,17.908],[-6.301,27.617],[-8.607,27.617],[-8.607,-14.228],[6.542,-27.617],[8.607,-27.617]],"c":true}},"nm":"Path 1","hd":false},{"ty":"gf","o":{"a":0,"k":100},"r":1,"bm":0,"g":{"p":3,"k":{"a":0,"k":[0,0.925,0.133,0.114,0.5,0.729,0.096,0.082,1,0.533,0.059,0.051]}},"s":{"a":0,"k":[-2.342,-13.455]},"e":{"a":0,"k":[1.502,13.309]},"t":1,"nm":"Gradient_AlokTMFCHM","hd":false},{"ty":"tr","p":{"a":0,"k":[0,0]},"a":{"a":0,"k":[0,0]},"s":{"a":0,"k":[100,100]},"r":{"a":0,"k":0},"o":{"a":0,"k":100},"sk":{"a":0,"k":0},"sa":{"a":0,"k":0},"nm":"Transform"}],"nm":"Group 1","bm":0,"hd":false}],"ip":0,"op":1,"st":0,"bm":0},{"ddd":0,"ind":8,"ty":4,"nm":"Слой 32","sr":1,"ks":{"p":{"a":0,"k":[247.31,319.566,0]}},"ao":0,"shapes":[{"ty":"gr","it":[{"ind":0,"ty":"sh","ks":{"a":0,"k":{"i":[[167.896,0],[0,0],[0,0],[-142.8,0],[-8.035,10.406],[0,0]],"o":[[-171.71,0],[0,0],[11.044,19.706],[155.203,0],[0,0],[0,0]],"v":[[0,18.226],[-214.438,-33.991],[-214.438,-21.798],[0,33.991],[214.438,-19.421],[214.438,-33.277]],"c":true}},"nm":"Path 1","hd":false},{"ty":"st","c":{"a":0,"k":[0.266666680574,0.023529412225,0.023529412225,1]},"o":{"a":0,"k":100},"w":{"a":0,"k":8},"lc":2,"lj":2,"bm":0,"nm":"Stroke 1","hd":false},{"ty":"tr","p":{"a":0,"k":[0,0]},"a":{"a":0,"k":[0,0]},"s":{"a":0,"k":[100,100]},"r":{"a":0,"k":0},"o":{"a":0,"k":100},"sk":{"a":0,"k":0},"sa":{"a":0,"k":0},"nm":"Transform"}],"nm":"Group 1","bm":0,"hd":false}],"ip":0,"op":1,"st":0,"bm":0},{"ddd":0,"ind":9,"ty":4,"nm":"Слой 31","sr":1,"ks":{"p":{"a":0,"k":[248.281,428.401,0]}},"ao":0,"shapes":[{"ty":"gr","it":[{"ind":0,"ty":"sh","ks":{"a":0,"k":{"i":[[3.54,0],[0,0],[0,-5.809],[-3.54,0],[0,0],[0,5.809]],"o":[[0,0],[-3.54,0],[0,5.809],[0,0],[3.54,0],[0,-5.809]],"v":[[42.421,-10.517],[-42.421,-10.517],[-48.83,0],[-42.421,10.517],[42.421,10.517],[48.83,0]],"c":true}},"nm":"Path 1","hd":false},{"ty":"st","c":{"a":0,"k":[0.176470592618,0.105882354081,0.074509806931,1]},"o":{"a":0,"k":100},"w":{"a":0,"k":8},"lc":1,"lj":1,"ml":10,"bm":0,"nm":"Stroke 1","hd":false},{"ty":"tr","p":{"a":0,"k":[0,0]},"a":{"a":0,"k":[0,0]},"s":{"a":0,"k":[100,100]},"r":{"a":0,"k":0},"o":{"a":0,"k":100},"sk":{"a":0,"k":0},"sa":{"a":0,"k":0},"nm":"Transform"}],"nm":"Group 1","bm":0,"hd":false}],"ip":0,"op":1,"st":0,"bm":0},{"ddd":0,"ind":10,"ty":4,"nm":"Слой 30","sr":1,"ks":{"p":{"a":0,"k":[247.271,278.361,0]}},"ao":0,"shapes":[{"ty":"gr","it":[{"ind":0,"ty":"sh","ks":{"a":0,"k":{"i":[[-86.769,1.217],[0.758,0.079],[102.237,0],[0,0],[1.185,-0.946]],"o":[[-1.242,-1.346],[0,0],[-102.237,0],[-1.122,0.152],[77.216,3.357]],"v":[[155.547,2.697],[152.449,0.414],[0.195,-4.159],[-152.059,0.414],[-155.547,2.148]],"c":true}},"nm":"Path 1","hd":false},{"ty":"gf","o":{"a":0,"k":100},"r":1,"bm":0,"g":{"p":3,"k":{"a":0,"k":[0,0.667,0.082,0.071,0.5,0.514,0.059,0.051,1,0.361,0.035,0.031]}},"s":{"a":0,"k":[-0.271,2.639]},"e":{"a":0,"k":[-0.615,-5.251]},"t":1,"nm":"Gradient_Ddzz4kFIwP","hd":false},{"ty":"tr","p":{"a":0,"k":[0,0]},"a":{"a":0,"k":[0,0]},"s":{"a":0,"k":[100,100]},"r":{"a":0,"k":0},"o":{"a":0,"k":100},"sk":{"a":0,"k":0},"sa":{"a":0,"k":0},"nm":"Transform"}],"nm":"Group 1","bm":0,"hd":false}],"ip":0,"op":1,"st":0,"bm":0},{"ddd":0,"ind":11,"ty":4,"nm":"Слой 29","sr":1,"ks":{"p":{"a":0,"k":[327.747,149.591,0]}},"ao":0,"shapes":[{"ty":"gr","it":[{"ind":0,"ty":"sh","ks":{"a":0,"k":{"i":[[0,0],[0,0],[2.941,0.992],[0,0]],"o":[[0,0],[-3.172,-1.336],[0,0],[0,0]],"v":[[10.489,68.503],[-1.301,-65.013],[-10.489,-68.503],[-4.492,68.503]],"c":true}},"nm":"Path 1","hd":false},{"ty":"gf","o":{"a":0,"k":100},"r":1,"bm":0,"g":{"p":3,"k":{"a":0,"k":[0.339,0.486,0.239,0.231,0.67,0.486,0.239,0.231,1,0.486,0.239,0.231,0.339,0.3,0.67,0.15,1,0]}},"s":{"a":0,"k":[-7.747,0.409]},"e":{"a":0,"k":[2.327,-0.164]},"t":1,"nm":"Gradient_CNNkGKqKXC","hd":false},{"ty":"tr","p":{"a":0,"k":[0,0]},"a":{"a":0,"k":[0,0]},"s":{"a":0,"k":[100,100]},"r":{"a":0,"k":0},"o":{"a":0,"k":100},"sk":{"a":0,"k":0},"sa":{"a":0,"k":0},"nm":"Transform"}],"nm":"Group 1","bm":0,"hd":false}],"ip":0,"op":1,"st":0,"bm":0},{"ddd":0,"ind":12,"ty":4,"nm":"Слой 28","sr":1,"ks":{"p":{"a":0,"k":[246.926,294.838,0]}},"ao":0,"shapes":[{"ty":"gr","it":[{"ind":0,"ty":"sh","ks":{"a":0,"k":{"i":[[3.187,0.333],[102.237,0],[0,0],[1.132,-3.161],[-99.032,0],[-28.035,9.964]],"o":[[0,0],[-102.237,0],[-5.833,0.793],[30.336,12.913],[96.002,0],[-1.014,-6.934]],"v":[[152.795,-16.063],[0.541,-20.636],[-151.713,-16.063],[-166.129,1.678],[0.384,20.636],[166.129,5.184]],"c":true}},"nm":"Path 1","hd":false},{"ty":"gf","o":{"a":0,"k":100},"r":1,"bm":0,"g":{"p":5,"k":{"a":0,"k":[0,0.486,0.067,0.055,0.266,0.7,0.11,0.092,0.532,0.914,0.153,0.129,0.766,0.755,0.127,0.108,1,0.596,0.102,0.086]}},"s":{"a":0,"k":[-135.926,-0.838]},"e":{"a":0,"k":[131.792,-0.838]},"t":1,"nm":"Gradient_Ni3W893LdP","hd":false},{"ty":"tr","p":{"a":0,"k":[0,0]},"a":{"a":0,"k":[0,0]},"s":{"a":0,"k":[100,100]},"r":{"a":0,"k":0},"o":{"a":0,"k":100},"sk":{"a":0,"k":0},"sa":{"a":0,"k":0},"nm":"Transform"}],"nm":"Group 1","bm":0,"hd":false}],"ip":0,"op":1,"st":0,"bm":0},{"ddd":0,"ind":13,"ty":4,"nm":"Слой 27","sr":1,"ks":{"p":{"a":0,"k":[165.539,149.374,0]}},"ao":0,"shapes":[{"ty":"gr","it":[{"ind":0,"ty":"sh","ks":{"a":0,"k":{"i":[[0,0],[0,0],[0,0],[2.966,-1.202]],"o":[[0,0],[0,0],[-2.745,0.931],[0,0]],"v":[[-11.823,68.286],[5.826,68.286],[11.823,-68.286],[3.241,-65.092]],"c":true}},"nm":"Path 1","hd":false},{"ty":"gf","o":{"a":0,"k":100},"r":1,"bm":0,"g":{"p":3,"k":{"a":0,"k":[0.264,0.486,0.239,0.231,0.632,0.486,0.239,0.231,1,0.486,0.239,0.231,0.264,0.3,0.632,0.15,1,0]}},"s":{"a":0,"k":[8.461,-0.374]},"e":{"a":0,"k":[-3.274,-1.183]},"t":1,"nm":"Gradient_90kUUVyAsD","hd":false},{"ty":"tr","p":{"a":0,"k":[0,0]},"a":{"a":0,"k":[0,0]},"s":{"a":0,"k":[100,100]},"r":{"a":0,"k":0},"o":{"a":0,"k":100},"sk":{"a":0,"k":0},"sa":{"a":0,"k":0},"nm":"Transform"}],"nm":"Group 1","bm":0,"hd":false}],"ip":0,"op":1,"st":0,"bm":0},{"ddd":0,"ind":14,"ty":4,"nm":"Слой 26","sr":1,"ks":{"p":{"a":0,"k":[247.31,76.877,0]}},"ao":0,"shapes":[{"ty":"gr","it":[{"ind":0,"ty":"sh","ks":{"a":0,"k":{"i":[[0,0],[-30.961,0],[-16.582,-10.13],[0,0],[30.961,0],[16.582,-10.13]],"o":[[16.582,-10.13],[30.961,0],[0,0],[-16.582,-10.13],[-30.961,0],[0,0]],"v":[[-69.948,14.779],[0,-4.211],[69.948,14.779],[69.948,4.211],[0,-14.779],[-69.948,4.211]],"c":true}},"nm":"Path 1","hd":false},{"ty":"gf","o":{"a":0,"k":100},"r":1,"bm":0,"g":{"p":3,"k":{"a":0,"k":[0,0.988,0.988,0.988,0.5,0.988,0.988,0.988,1,0.988,0.988,0.988,0,0.7,0.5,0.35,1,0]}},"s":{"a":0,"k":[-1.31,-22.877]},"e":{"a":0,"k":[-95.653,-20.884]},"t":2,"h":{"a":0,"k":0},"a":{"a":0,"k":0},"nm":"Gradient_zffVNPyYOI","hd":false},{"ty":"tr","p":{"a":0,"k":[0,0]},"a":{"a":0,"k":[0,0]},"s":{"a":0,"k":[100,100]},"r":{"a":0,"k":0},"o":{"a":0,"k":100},"sk":{"a":0,"k":0},"sa":{"a":0,"k":0},"nm":"Transform"}],"nm":"Group 1","bm":0,"hd":false}],"ip":0,"op":1,"st":0,"bm":0},{"ddd":0,"ind":15,"ty":4,"nm":"Слой 25","sr":1,"ks":{"p":{"a":0,"k":[247.326,90.631,0]}},"ao":0,"shapes":[{"ty":"gr","it":[{"ind":0,"ty":"sh","ks":{"a":0,"k":{"i":[[16.582,-10.13],[0,0],[-35.793,-28.209],[0,0],[30.961,0]],"o":[[0,0],[44.469,-28.237],[0,0],[-16.582,-10.13],[-30.961,0]],"v":[[-69.964,-9.543],[-71.599,27.802],[71.599,28.533],[69.932,-9.543],[-0.016,-28.533]],"c":true}},"nm":"Path 1","hd":false},{"ty":"gf","o":{"a":0,"k":100},"r":1,"bm":0,"g":{"p":3,"k":{"a":0,"k":[0.927,0.729,0.478,0.475,0.963,0.729,0.478,0.475,1,0.729,0.478,0.475,0.927,0,0.963,0.15,1,0.3]}},"s":{"a":0,"k":[-0.326,130.369]},"e":{"a":0,"k":[-0.326,-3.28]},"t":2,"h":{"a":0,"k":0},"a":{"a":0,"k":0},"nm":"Gradient_IhXZ0w2O3G","hd":false},{"ty":"tr","p":{"a":0,"k":[0,0]},"a":{"a":0,"k":[0,0]},"s":{"a":0,"k":[100,100]},"r":{"a":0,"k":0},"o":{"a":0,"k":100},"sk":{"a":0,"k":0},"sa":{"a":0,"k":0},"nm":"Transform"}],"nm":"Group 1","bm":0,"hd":false}],"ip":0,"op":1,"st":0,"bm":0},{"ddd":0,"ind":16,"ty":4,"nm":"Слой 24","sr":1,"ks":{"p":{"a":0,"k":[248.281,428.401,0]}},"ao":0,"shapes":[{"ty":"gr","it":[{"ind":0,"ty":"sh","ks":{"a":0,"k":{"i":[[3.54,0],[0,0],[0,-5.809],[-3.54,0],[0,0],[0,5.809]],"o":[[0,0],[-3.54,0],[0,5.809],[0,0],[3.54,0],[0,-5.809]],"v":[[42.421,-10.517],[-42.421,-10.517],[-48.83,0],[-42.421,10.517],[42.421,10.517],[48.83,0]],"c":true}},"nm":"Path 1","hd":false},{"ty":"gf","o":{"a":0,"k":100},"r":1,"bm":0,"g":{"p":5,"k":{"a":0,"k":[0,0.427,0.306,0.235,0.213,0.433,0.316,0.239,0.426,0.439,0.325,0.243,0.713,0.361,0.251,0.182,1,0.282,0.176,0.122]}},"s":{"a":0,"k":[-0.281,-8.401]},"e":{"a":0,"k":[-0.281,4.19]},"t":1,"nm":"Gradient_iMM3z1xtru","hd":false},{"ty":"tr","p":{"a":0,"k":[0,0]},"a":{"a":0,"k":[0,0]},"s":{"a":0,"k":[100,100]},"r":{"a":0,"k":0},"o":{"a":0,"k":100},"sk":{"a":0,"k":0},"sa":{"a":0,"k":0},"nm":"Transform"}],"nm":"Group 1","bm":0,"hd":false}],"ip":0,"op":1,"st":0,"bm":0},{"ddd":0,"ind":17,"ty":4,"nm":"Слой 23","sr":1,"ks":{"p":{"a":0,"k":[247.31,320.066,0]}},"ao":0,"shapes":[{"ty":"gr","it":[{"ind":0,"ty":"sh","ks":{"a":0,"k":{"i":[[167.896,0],[0,0],[0,0],[-142.8,0],[-8.035,10.406],[0,0]],"o":[[-171.71,0],[0,0],[11.044,19.706],[155.203,0],[0,0],[0,0]],"v":[[0,19.726],[-214.438,-34.491],[-214.438,-22.298],[0,34.491],[214.438,-19.921],[214.438,-33.777]],"c":true}},"nm":"Path 1","hd":false},{"ty":"gf","o":{"a":0,"k":100},"r":1,"bm":0,"g":{"p":9,"k":{"a":0,"k":[0,0.576,0.078,0.067,0.135,0.555,0.084,0.071,0.27,0.533,0.09,0.075,0.395,0.763,0.245,0.227,0.521,0.992,0.4,0.38,0.628,0.775,0.247,0.231,0.735,0.557,0.094,0.082,0.868,0.606,0.094,0.08,1,0.655,0.094,0.078]}},"s":{"a":0,"k":[-215.31,-0.066]},"e":{"a":0,"k":[213.565,-0.066]},"t":1,"nm":"Gradient_v1KD9XmGCZ","hd":false},{"ty":"tr","p":{"a":0,"k":[0,0]},"a":{"a":0,"k":[0,0]},"s":{"a":0,"k":[100,100]},"r":{"a":0,"k":0},"o":{"a":0,"k":100},"sk":{"a":0,"k":0},"sa":{"a":0,"k":0},"nm":"Transform"}],"nm":"Group 1","bm":0,"hd":false}],"ip":0,"op":1,"st":0,"bm":0},{"ddd":0,"ind":18,"ty":4,"nm":"Слой 22","sr":1,"ks":{"p":{"a":0,"k":[247.31,161.098,0]}},"ao":0,"shapes":[{"ty":"gr","it":[{"ind":0,"ty":"sh","ks":{"a":0,"k":{"i":[[0,0],[0,0],[0,0],[0,0],[0,0],[0,0],[0,0],[0,0],[0,0],[0,0],[0,0],[0,0]],"o":[[0,0],[0,0],[0,0],[0,0],[0,0],[0,0],[0,0],[0,0],[0,0],[0,0],[0,0],[0,0]],"v":[[61.115,12.963],[60.89,-19.032],[17.122,-19.032],[17.053,-56.562],[-17.053,-56.562],[-17.122,-19.032],[-60.89,-19.032],[-61.115,12.963],[-17.18,12.963],[-17.259,56.562],[17.259,56.562],[17.18,12.963]],"c":true}},"nm":"Path 1","hd":false},{"ty":"fl","c":{"a":0,"k":[0.988235294819,0.988235294819,0.988235294819,1]},"o":{"a":0,"k":100},"r":1,"bm":0,"nm":"Fill 1","hd":false},{"ty":"tr","p":{"a":0,"k":[0,0]},"a":{"a":0,"k":[0,0]},"s":{"a":0,"k":[100,100]},"r":{"a":0,"k":0},"o":{"a":0,"k":100},"sk":{"a":0,"k":0},"sa":{"a":0,"k":0},"nm":"Transform"}],"nm":"Group 1","bm":0,"hd":false}],"ip":0,"op":1,"st":0,"bm":0},{"ddd":0,"ind":19,"ty":4,"nm":"Слой 21","sr":1,"ks":{"p":{"a":0,"k":[247.31,140.096,0]}},"ao":0,"shapes":[{"ty":"gr","it":[{"ind":0,"ty":"sh","ks":{"a":0,"k":{"i":[[0,0],[0,0],[30.961,0],[16.582,-10.13],[0,0]],"o":[[0,0],[-16.582,-10.13],[-30.961,0],[0,0],[0,0]],"v":[[75.945,77.998],[69.948,-59.008],[0,-77.998],[-69.948,-59.008],[-75.945,77.998]],"c":false}},"nm":"Path 1","hd":false},{"ty":"gf","o":{"a":0,"k":100},"r":1,"bm":0,"g":{"p":7,"k":{"a":0,"k":[0,0.992,0.337,0.318,0.109,0.992,0.337,0.318,0.219,0.992,0.337,0.318,0.413,0.875,0.288,0.273,0.608,0.757,0.239,0.227,0.804,0.775,0.278,0.267,1,0.792,0.318,0.306,0,0,0.109,0.5,0.219,1,0.413,1,0.608,1,0.804,1,1,1]}},"s":{"a":0,"k":[-0.31,71.904]},"e":{"a":0,"k":[-0.31,-78.894]},"t":1,"nm":"Gradient_Z7txdbVHDy","hd":false},{"ty":"tr","p":{"a":0,"k":[0,0]},"a":{"a":0,"k":[0,0]},"s":{"a":0,"k":[100,100]},"r":{"a":0,"k":0},"o":{"a":0,"k":100},"sk":{"a":0,"k":0},"sa":{"a":0,"k":0},"nm":"Transform"}],"nm":"Group 1","bm":0,"hd":false}],"ip":0,"op":1,"st":0,"bm":0},{"ddd":0,"ind":20,"ty":4,"nm":"Слой 20","sr":1,"ks":{"p":{"a":0,"k":[247.254,117.371,0]}},"ao":0,"shapes":[{"ty":"gr","it":[{"ind":0,"ty":"sh","ks":{"a":0,"k":{"i":[[-16.37,29.99],[-25.063,8.505],[0,0],[0,0],[-24.261,-43.241]],"o":[[24.347,-44.605],[0,0],[0,0],[25.368,8.56],[17.353,30.929]],"v":[[-154.797,35.791],[-69.892,-36.283],[0.056,-36.283],[70.004,-36.283],[154.797,36.283]],"c":false}},"nm":"Path 1","hd":false},{"ty":"st","c":{"a":0,"k":[0.419607847929,0.082352943718,0.082352943718,1]},"o":{"a":0,"k":100},"w":{"a":0,"k":8},"lc":2,"lj":2,"bm":0,"nm":"Stroke 1","hd":false},{"ty":"tr","p":{"a":0,"k":[0,0]},"a":{"a":0,"k":[0,0]},"s":{"a":0,"k":[100,100]},"r":{"a":0,"k":0},"o":{"a":0,"k":100},"sk":{"a":0,"k":0},"sa":{"a":0,"k":0},"nm":"Transform"}],"nm":"Group 1","bm":0,"hd":false}],"ip":0,"op":1,"st":0,"bm":0},{"ddd":0,"ind":21,"ty":4,"nm":"Слой 19","sr":1,"ks":{"p":{"a":0,"k":[247.467,182.893,0]}},"ao":0,"shapes":[{"ty":"gr","it":[{"ind":0,"ty":"sh","ks":{"a":0,"k":{"i":[[0.01,2.155],[-41.914,14.224],[0,0],[0,0],[3.304,-138.337]],"o":[[-0.671,-143.734],[0,0],[0,0],[43.513,14.683],[-0.066,2.749]],"v":[[-182.439,99.627],[-70.105,-101.805],[-0.157,-101.805],[69.791,-101.805],[182.334,101.805]],"c":false}},"nm":"Path 1","hd":false},{"ty":"st","c":{"a":0,"k":[0.309803932905,0.027450980619,0.027450980619,1]},"o":{"a":0,"k":100},"w":{"a":0,"k":8},"lc":2,"lj":2,"bm":0,"nm":"Stroke 1","hd":false},{"ty":"tr","p":{"a":0,"k":[0,0]},"a":{"a":0,"k":[0,0]},"s":{"a":0,"k":[100,100]},"r":{"a":0,"k":0},"o":{"a":0,"k":100},"sk":{"a":0,"k":0},"sa":{"a":0,"k":0},"nm":"Transform"}],"nm":"Group 1","bm":0,"hd":false}],"ip":0,"op":1,"st":0,"bm":0},{"ddd":0,"ind":22,"ty":4,"nm":"Слой 18","sr":1,"ks":{"p":{"a":0,"k":[360.638,124.899,0]}},"ao":0,"shapes":[{"ty":"gr","it":[{"ind":0,"ty":"sh","ks":{"a":0,"k":{"i":[[-1.129,-3.2],[-2.502,-11.493],[-9.298,4.831],[-3.45,0.565],[-9.453,-6.141],[26.064,8.795],[0,0]],"o":[[1.129,3.2],[1.937,8.899],[7.974,-4.144],[2.07,-0.339],[-24.296,-45.704],[0,0],[24.319,11.096]],"v":[[-4.361,8.85],[-7.322,29.753],[14.334,42.418],[23.435,22.779],[43.38,32.379],[-43.38,-43.811],[-41.857,-9.023]],"c":true}},"nm":"Path 1","hd":false},{"ty":"gf","o":{"a":0,"k":100},"r":1,"bm":0,"g":{"p":3,"k":{"a":0,"k":[0,0.749,0.384,0.384,0.5,0.749,0.384,0.384,1,0.749,0.384,0.384,0,0.7,0.5,0.35,1,0]}},"s":{"a":0,"k":[4.362,-16.899]},"e":{"a":0,"k":[-10.228,18.739]},"t":1,"nm":"Gradient_iUyXZrSZSC","hd":false},{"ty":"tr","p":{"a":0,"k":[0,0]},"a":{"a":0,"k":[0,0]},"s":{"a":0,"k":[100,100]},"r":{"a":0,"k":0},"o":{"a":0,"k":100},"sk":{"a":0,"k":0},"sa":{"a":0,"k":0},"nm":"Transform"}],"nm":"Group 1","bm":0,"hd":false}],"ip":0,"op":1,"st":0,"bm":0},{"ddd":0,"ind":23,"ty":4,"nm":"Слой 17","sr":1,"ks":{"p":{"a":0,"k":[359.707,117.151,0]}},"ao":0,"shapes":[{"ty":"gr","it":[{"ind":0,"ty":"sh","ks":{"a":0,"k":{"i":[[1.419,0.036],[21.548,7.436],[0,0],[-24.347,-44.602]],"o":[[-24.519,-33.552],[0,0],[25.062,8.505],[-1.466,0.059]],"v":[[38.131,36.036],[-41.969,-25.092],[-42.449,-36.063],[42.449,36.018]],"c":true}},"nm":"Path 1","hd":false},{"ty":"gf","o":{"a":0,"k":100},"r":1,"bm":0,"g":{"p":3,"k":{"a":0,"k":[0,0.988,0.988,0.988,0.5,0.988,0.988,0.988,1,0.988,0.988,0.988,0,0.7,0.5,0.35,1,0]}},"s":{"a":0,"k":[1119.707,-45.151]},"e":{"a":0,"k":[1195.891,-121.335]},"t":2,"h":{"a":0,"k":0},"a":{"a":0,"k":0},"nm":"Gradient_PU5XuWJIrt","hd":false},{"ty":"tr","p":{"a":0,"k":[0,0]},"a":{"a":0,"k":[0,0]},"s":{"a":0,"k":[100,100]},"r":{"a":0,"k":0},"o":{"a":0,"k":100},"sk":{"a":0,"k":0},"sa":{"a":0,"k":0},"nm":"Transform"}],"nm":"Group 1","bm":0,"hd":false}],"ip":0,"op":1,"st":0,"bm":0},{"ddd":0,"ind":24,"ty":4,"nm":"Слой 16","sr":1,"ks":{"p":{"a":0,"k":[134.914,117.151,0]}},"ao":0,"shapes":[{"ty":"gr","it":[{"ind":0,"ty":"sh","ks":{"a":0,"k":{"i":[[-1.419,0.036],[-21.548,7.436],[0,0],[24.347,-44.602]],"o":[[24.519,-33.552],[0,0],[-25.062,8.505],[1.466,0.059]],"v":[[-38.131,36.036],[41.969,-25.092],[42.449,-36.063],[-42.449,36.018]],"c":true}},"nm":"Path 1","hd":false},{"ty":"gf","o":{"a":0,"k":100},"r":1,"bm":0,"g":{"p":3,"k":{"a":0,"k":[0,0.988,0.988,0.988,0.5,0.988,0.988,0.988,1,0.988,0.988,0.988,0,0.7,0.5,0.35,1,0]}},"s":{"a":0,"k":[45.086,-45.151]},"e":{"a":0,"k":[-31.098,31.033]},"t":2,"h":{"a":0,"k":0},"a":{"a":0,"k":0},"nm":"Gradient_gAnpUMkmhW","hd":false},{"ty":"tr","p":{"a":0,"k":[0,0]},"a":{"a":0,"k":[0,0]},"s":{"a":0,"k":[100,100]},"r":{"a":0,"k":0},"o":{"a":0,"k":100},"sk":{"a":0,"k":0},"sa":{"a":0,"k":0},"nm":"Transform"}],"nm":"Group 1","bm":0,"hd":false}],"ip":0,"op":1,"st":0,"bm":0},{"ddd":0,"ind":25,"ty":4,"nm":"Слой 15","sr":1,"ks":{"p":{"a":0,"k":[134.914,117.156,0]}},"ao":0,"shapes":[{"ty":"gr","it":[{"ind":0,"ty":"sh","ks":{"a":0,"k":{"i":[[24.347,-44.602],[-32.501,18.648],[0,0]],"o":[[31.001,1.25],[0,0],[-25.062,8.505]],"v":[[-42.449,36.013],[40.957,-1.993],[42.449,-36.067]],"c":true}},"nm":"Path 1","hd":false},{"ty":"gf","o":{"a":0,"k":100},"r":1,"bm":0,"g":{"p":3,"k":{"a":0,"k":[0,0.749,0.384,0.384,0.5,0.749,0.384,0.384,1,0.749,0.384,0.384,0,0.7,0.5,0.35,1,0]}},"s":{"a":0,"k":[-6.914,-13.156]},"e":{"a":0,"k":[15.502,27.536]},"t":1,"nm":"Gradient_5NhzgCZvHW","hd":false},{"ty":"tr","p":{"a":0,"k":[0,0]},"a":{"a":0,"k":[0,0]},"s":{"a":0,"k":[100,100]},"r":{"a":0,"k":0},"o":{"a":0,"k":100},"sk":{"a":0,"k":0},"sa":{"a":0,"k":0},"nm":"Transform"}],"nm":"Group 1","bm":0,"hd":false}],"ip":0,"op":1,"st":0,"bm":0},{"ddd":0,"ind":26,"ty":4,"nm":"Слой 14","sr":1,"ks":{"p":{"a":0,"k":[384.073,200.523,0]}},"ao":0,"shapes":[{"ty":"gr","it":[{"ind":0,"ty":"sh","ks":{"a":0,"k":{"i":[[33.563,-11.737],[0,0],[-12.929,4.595],[-3.771,6.618],[0,0],[43.363,23.092]],"o":[[0,0],[22.728,-2.592],[0,0],[0,0],[5.533,-123.574],[42.715,55.546]],"v":[[-22.51,75.948],[-22.518,110.327],[28.981,99.498],[37.013,80.624],[45.44,92.525],[-45.837,-110.327]],"c":true}},"nm":"Path 1","hd":false},{"ty":"gf","o":{"a":0,"k":100},"r":1,"bm":0,"g":{"p":3,"k":{"a":0,"k":[0,0.537,0.09,0.082,0.5,0.537,0.09,0.082,1,0.537,0.09,0.082,0,0.8,0.5,0.4,1,0]}},"s":{"a":0,"k":[16.927,53.477]},"e":{"a":0,"k":[-28.838,-96.973]},"t":2,"h":{"a":0,"k":0},"a":{"a":0,"k":0},"nm":"Gradient_2AIeO7kTqF","hd":false},{"ty":"tr","p":{"a":0,"k":[0,0]},"a":{"a":0,"k":[0,0]},"s":{"a":0,"k":[100,100]},"r":{"a":0,"k":0},"o":{"a":0,"k":100},"sk":{"a":0,"k":0},"sa":{"a":0,"k":0},"nm":"Transform"}],"nm":"Group 1","bm":0,"hd":false}],"ip":0,"op":1,"st":0,"bm":0},{"ddd":0,"ind":27,"ty":4,"nm":"Слой 13","sr":1,"ks":{"p":{"a":0,"k":[121.193,188.802,0]}},"ao":0,"shapes":[{"ty":"gr","it":[{"ind":0,"ty":"sh","ks":{"a":0,"k":{"i":[[-2.888,-148.955],[0,0],[0,0],[0,0],[-70.991,51.953]],"o":[[0,0],[0,0],[0,0],[-31,-32.712],[-42.542,14.437]],"v":[[-56.086,100.25],[-44.244,98.562],[-40.396,107.714],[3.37,87.893],[56.17,-107.714]],"c":true}},"nm":"Path 1","hd":false},{"ty":"gf","o":{"a":0,"k":100},"r":1,"bm":0,"g":{"p":3,"k":{"a":0,"k":[0,0.427,0.063,0.051,0.5,0.427,0.063,0.051,1,0.427,0.063,0.051,0,0.8,0.5,0.4,1,0]}},"s":{"a":0,"k":[-48.193,29.198]},"e":{"a":0,"k":[6.019,-89.39]},"t":2,"h":{"a":0,"k":0},"a":{"a":0,"k":0},"nm":"Gradient_fXCf8i0Tp9","hd":false},{"ty":"tr","p":{"a":0,"k":[0,0]},"a":{"a":0,"k":[0,0]},"s":{"a":0,"k":[100,100]},"r":{"a":0,"k":0},"o":{"a":0,"k":100},"sk":{"a":0,"k":0},"sa":{"a":0,"k":0},"nm":"Transform"}],"nm":"Group 1","bm":0,"hd":false}],"ip":0,"op":1,"st":0,"bm":0},{"ddd":0,"ind":28,"ty":4,"nm":"Слой 12","sr":1,"ks":{"p":{"a":0,"k":[247.467,198.281,0]}},"ao":0,"shapes":[{"ty":"gr","it":[{"ind":0,"ty":"sh","ks":{"a":0,"k":{"i":[[0,0],[-42.542,14.437],[0,0],[0,0],[6.477,-144.663],[0,0],[0,0],[96.002,0],[30.335,12.913],[0,0]],"o":[[-2.888,-148.955],[0,0],[0,0],[44.378,14.975],[0,0],[-3.771,6.618],[-28.035,9.964],[-99.032,0],[0,0],[0,0]],"v":[[-182.36,90.771],[-70.105,-117.193],[-0.157,-117.193],[69.791,-117.193],[182.047,94.767],[173.619,82.866],[165.588,101.74],[-0.157,117.193],[-166.67,98.235],[-170.518,89.083]],"c":true}},"nm":"Path 1","hd":false},{"ty":"gf","o":{"a":0,"k":100},"r":1,"bm":0,"g":{"p":3,"k":{"a":0,"k":[0.175,0.984,0.184,0.165,0.588,0.765,0.135,0.12,1,0.545,0.086,0.075]}},"s":{"a":0,"k":[-0.467,28.719]},"e":{"a":0,"k":[-0.467,-145.104]},"t":2,"h":{"a":0,"k":0},"a":{"a":0,"k":0},"nm":"Gradient_VBVp9vcToU","hd":false},{"ty":"tr","p":{"a":0,"k":[0,0]},"a":{"a":0,"k":[0,0]},"s":{"a":0,"k":[100,100]},"r":{"a":0,"k":0},"o":{"a":0,"k":100},"sk":{"a":0,"k":0},"sa":{"a":0,"k":0},"nm":"Transform"}],"nm":"Group 1","bm":0,"hd":false}],"ip":0,"op":1,"st":0,"bm":0},{"ddd":0,"ind":29,"ty":4,"nm":"Слой 11","sr":1,"ks":{"p":{"a":0,"k":[97.562,344.504,0]}},"ao":0,"shapes":[{"ty":"gr","it":[{"ind":0,"ty":"sh","ks":{"a":0,"k":{"i":[[9.513,16.703],[1.03,10.288],[0,0],[-7.128,-10.29]],"o":[[-9.865,-17.323],[0,0],[5.573,12.622],[12.235,17.663]],"v":[[0.204,22.075],[-15.977,-22.075],[-3.127,-15.286],[15.977,19.151]],"c":false}},"nm":"Path 1","hd":false},{"ty":"st","c":{"a":0,"k":[0.086274512112,0.043137256056,0.035294119269,1]},"o":{"a":0,"k":100},"w":{"a":0,"k":8},"lc":2,"lj":2,"bm":0,"nm":"Stroke 1","hd":false},{"ty":"tr","p":{"a":0,"k":[0,0]},"a":{"a":0,"k":[0,0]},"s":{"a":0,"k":[100,100]},"r":{"a":0,"k":0},"o":{"a":0,"k":100},"sk":{"a":0,"k":0},"sa":{"a":0,"k":0},"nm":"Transform"}],"nm":"Group 1","bm":0,"hd":false}],"ip":0,"op":1,"st":0,"bm":0},{"ddd":0,"ind":30,"ty":4,"nm":"Слой 10","sr":1,"ks":{"p":{"a":0,"k":[144.92,379.367,0]}},"ao":0,"shapes":[{"ty":"gr","it":[{"ind":0,"ty":"sh","ks":{"a":0,"k":{"i":[[0,0],[-48.089,-0.85],[0,0],[3.017,30.128]],"o":[[24.706,55.955],[0,0],[-84.137,0],[0,0]],"v":[[-50.485,-50.148],[63.335,41.045],[63.335,56.938],[-63.335,-56.938]],"c":true}},"nm":"Path 1","hd":false},{"ty":"st","c":{"a":0,"k":[0.176470592618,0.090196080506,0.070588238537,1]},"o":{"a":0,"k":100},"w":{"a":0,"k":8},"lc":2,"lj":2,"bm":0,"nm":"Stroke 1","hd":false},{"ty":"tr","p":{"a":0,"k":[0,0]},"a":{"a":0,"k":[0,0]},"s":{"a":0,"k":[100,100]},"r":{"a":0,"k":0},"o":{"a":0,"k":100},"sk":{"a":0,"k":0},"sa":{"a":0,"k":0},"nm":"Transform"}],"nm":"Group 1","bm":0,"hd":false}],"ip":0,"op":1,"st":0,"bm":0},{"ddd":0,"ind":31,"ty":4,"nm":"Слой 9","sr":1,"ks":{"p":{"a":0,"k":[157.954,390.824,0]}},"ao":0,"shapes":[{"ty":"gr","it":[{"ind":0,"ty":"sh","ks":{"a":0,"k":{"i":[[-42.017,-0.742],[0,0],[24.933,40.813]],"o":[[0,0],[-40.321,-0.712],[12.924,43.098]],"v":[[46.209,36.238],[50.302,29.588],[-50.302,-36.238]],"c":true}},"nm":"Path 1","hd":false},{"ty":"fl","c":{"a":0,"k":[0.443137258291,0.290196090937,0.207843139768,1]},"o":{"a":0,"k":100},"r":1,"bm":0,"nm":"Fill 1","hd":false},{"ty":"tr","p":{"a":0,"k":[0,0]},"a":{"a":0,"k":[0,0]},"s":{"a":0,"k":[100,100]},"r":{"a":0,"k":0},"o":{"a":0,"k":100},"sk":{"a":0,"k":0},"sa":{"a":0,"k":0},"nm":"Transform"}],"nm":"Group 1","bm":0,"hd":false}],"ip":0,"op":1,"st":0,"bm":0},{"ddd":0,"ind":32,"ty":4,"nm":"Слой 8","sr":1,"ks":{"p":{"a":0,"k":[144.92,379.367,0]}},"ao":0,"shapes":[{"ty":"gr","it":[{"ind":0,"ty":"sh","ks":{"a":0,"k":{"i":[[0,0],[-48.089,-0.85],[0,0],[3.017,30.128]],"o":[[24.706,55.955],[0,0],[-84.137,0],[0,0]],"v":[[-50.485,-50.148],[63.335,41.045],[63.335,56.938],[-63.335,-56.938]],"c":true}},"nm":"Path 1","hd":false},{"ty":"gf","o":{"a":0,"k":100},"r":1,"bm":0,"g":{"p":3,"k":{"a":0,"k":[0,0.314,0.192,0.133,0.5,0.241,0.143,0.098,1,0.169,0.094,0.063]}},"s":{"a":0,"k":[-0.92,-3.367]},"e":{"a":0,"k":[-22.944,-47.414]},"t":1,"nm":"Gradient_GHEde6pUjv","hd":false},{"ty":"tr","p":{"a":0,"k":[0,0]},"a":{"a":0,"k":[0,0]},"s":{"a":0,"k":[100,100]},"r":{"a":0,"k":0},"o":{"a":0,"k":100},"sk":{"a":0,"k":0},"sa":{"a":0,"k":0},"nm":"Transform"}],"nm":"Group 1","bm":0,"hd":false}],"ip":0,"op":1,"st":0,"bm":0},{"ddd":0,"ind":33,"ty":4,"nm":"Слой 7","sr":1,"ks":{"p":{"a":0,"k":[403.365,337.494,0]}},"ao":0,"shapes":[{"ty":"gr","it":[{"ind":0,"ty":"sh","ks":{"a":0,"k":{"i":[[-10.962,22.713],[-0.784,7.834],[0,0],[4.169,-6.991]],"o":[[6.163,-12.769],[0,0],[-3.479,7.88],[-0.605,1.015]],"v":[[2.269,16.065],[12.671,-16.065],[-1.18,-8.275],[-12.671,14.049]],"c":false}},"nm":"Path 1","hd":false},{"ty":"st","c":{"a":0,"k":[0.086274512112,0.043137256056,0.035294119269,1]},"o":{"a":0,"k":100},"w":{"a":0,"k":8},"lc":2,"lj":2,"bm":0,"nm":"Stroke 1","hd":false},{"ty":"tr","p":{"a":0,"k":[0,0]},"a":{"a":0,"k":[0,0]},"s":{"a":0,"k":[100,100]},"r":{"a":0,"k":0},"o":{"a":0,"k":100},"sk":{"a":0,"k":0},"sa":{"a":0,"k":0},"nm":"Transform"}],"nm":"Group 1","bm":0,"hd":false}],"ip":0,"op":1,"st":0,"bm":0},{"ddd":0,"ind":34,"ty":4,"nm":"Слой 6","sr":1,"ks":{"p":{"a":0,"k":[351.201,378.867,0]}},"ao":0,"shapes":[{"ty":"gr","it":[{"ind":0,"ty":"sh","ks":{"a":0,"k":{"i":[[0,0],[48.089,-0.85],[0,0],[-3.017,30.128]],"o":[[-24.706,55.955],[0,0],[84.137,0],[0,0]],"v":[[50.985,-49.648],[-64.835,41.545],[-64.835,57.438],[64.835,-57.438]],"c":true}},"nm":"Path 1","hd":false},{"ty":"st","c":{"a":0,"k":[0.176470592618,0.090196080506,0.070588238537,1]},"o":{"a":0,"k":100},"w":{"a":0,"k":8},"lc":2,"lj":2,"bm":0,"nm":"Stroke 1","hd":false},{"ty":"tr","p":{"a":0,"k":[0,0]},"a":{"a":0,"k":[0,0]},"s":{"a":0,"k":[100,100]},"r":{"a":0,"k":0},"o":{"a":0,"k":100},"sk":{"a":0,"k":0},"sa":{"a":0,"k":0},"nm":"Transform"}],"nm":"Group 1","bm":0,"hd":false}],"ip":0,"op":1,"st":0,"bm":0},{"ddd":0,"ind":35,"ty":4,"nm":"Слой 5","sr":1,"ks":{"p":{"a":0,"k":[337.609,390.837,0]}},"ao":0,"shapes":[{"ty":"gr","it":[{"ind":0,"ty":"sh","ks":{"a":0,"k":{"i":[[0,0],[-10.185,40.387],[40.333,-0.713]],"o":[[44.209,-0.781],[-25.388,40.835],[0,0]],"v":[[-48.745,36.288],[51.243,-36.288],[-51.243,29.575]],"c":true}},"nm":"Path 1","hd":false},{"ty":"fl","c":{"a":0,"k":[0.411764711142,0.266666680574,0.188235297799,1]},"o":{"a":0,"k":100},"r":1,"bm":0,"nm":"Fill 1","hd":false},{"ty":"tr","p":{"a":0,"k":[0,0]},"a":{"a":0,"k":[0,0]},"s":{"a":0,"k":[100,100]},"r":{"a":0,"k":0},"o":{"a":0,"k":100},"sk":{"a":0,"k":0},"sa":{"a":0,"k":0},"nm":"Transform"}],"nm":"Group 1","bm":0,"hd":false}],"ip":0,"op":1,"st":0,"bm":0},{"ddd":0,"ind":36,"ty":4,"nm":"Слой 4","sr":1,"ks":{"p":{"a":0,"k":[351.201,378.867,0]}},"ao":0,"shapes":[{"ty":"gr","it":[{"ind":0,"ty":"sh","ks":{"a":0,"k":{"i":[[0,0],[48.089,-0.85],[0,0],[-3.017,30.128]],"o":[[-24.706,55.955],[0,0],[84.137,0],[0,0]],"v":[[50.985,-49.648],[-64.835,41.545],[-64.835,57.438],[64.835,-57.438]],"c":true}},"nm":"Path 1","hd":false},{"ty":"gf","o":{"a":0,"k":100},"r":1,"bm":0,"g":{"p":3,"k":{"a":0,"k":[0,0.314,0.192,0.133,0.5,0.241,0.143,0.098,1,0.169,0.094,0.063]}},"s":{"a":0,"k":[-0.201,-10.867]},"e":{"a":0,"k":[6.41,-44.473]},"t":1,"nm":"Gradient_NnYzAkAdb5","hd":false},{"ty":"tr","p":{"a":0,"k":[0,0]},"a":{"a":0,"k":[0,0]},"s":{"a":0,"k":[100,100]},"r":{"a":0,"k":0},"o":{"a":0,"k":100},"sk":{"a":0,"k":0},"sa":{"a":0,"k":0},"nm":"Transform"}],"nm":"Group 1","bm":0,"hd":false}],"ip":0,"op":1,"st":0,"bm":0},{"ddd":0,"ind":37,"ty":4,"nm":"Слой 3","sr":1,"ks":{"p":{"a":0,"k":[247.31,310.797,0]}},"ao":0,"shapes":[{"ty":"gr","it":[{"ind":0,"ty":"sh","ks":{"a":0,"k":{"i":[[152.256,0],[0,0],[-171.71,0],[0,0]],"o":[[-152.256,0],[0,0],[167.896,0],[0,0]],"v":[[0,-28.995],[-214.438,-25.223],[0,28.995],[214.438,-24.508]],"c":true}},"nm":"Path 1","hd":false},{"ty":"st","c":{"a":0,"k":[0.266666680574,0.023529412225,0.023529412225,1]},"o":{"a":0,"k":100},"w":{"a":0,"k":8},"lc":2,"lj":2,"bm":0,"nm":"Stroke 1","hd":false},{"ty":"tr","p":{"a":0,"k":[0,0]},"a":{"a":0,"k":[0,0]},"s":{"a":0,"k":[100,100]},"r":{"a":0,"k":0},"o":{"a":0,"k":100},"sk":{"a":0,"k":0},"sa":{"a":0,"k":0},"nm":"Transform"}],"nm":"Group 1","bm":0,"hd":false}],"ip":0,"op":1,"st":0,"bm":0},{"ddd":0,"ind":38,"ty":4,"nm":"Слой 2","sr":1,"ks":{"p":{"a":0,"k":[247.31,310.797,0]}},"ao":0,"shapes":[{"ty":"gr","it":[{"ind":0,"ty":"sh","ks":{"a":0,"k":{"i":[[152.256,0],[0,0],[-171.71,0],[0,0]],"o":[[-152.256,0],[0,0],[167.896,0],[0,0]],"v":[[0,-28.995],[-214.438,-25.223],[0,28.995],[214.438,-24.508]],"c":true}},"nm":"Path 1","hd":false},{"ty":"gf","o":{"a":0,"k":100},"r":1,"bm":0,"g":{"p":5,"k":{"a":0,"k":[0,0.439,0.047,0.039,0.255,0.467,0.049,0.041,0.51,0.494,0.051,0.043,0.755,0.467,0.049,0.041,1,0.439,0.047,0.039]}},"s":{"a":0,"k":[-215.31,-0.797]},"e":{"a":0,"k":[213.565,-0.797]},"t":1,"nm":"Gradient_qxqXktC4gG","hd":false},{"ty":"tr","p":{"a":0,"k":[0,0]},"a":{"a":0,"k":[0,0]},"s":{"a":0,"k":[100,100]},"r":{"a":0,"k":0},"o":{"a":0,"k":100},"sk":{"a":0,"k":0},"sa":{"a":0,"k":0},"nm":"Transform"}],"nm":"Group 1","bm":0,"hd":false}],"ip":0,"op":1,"st":0,"bm":0},{"ddd":0,"ind":39,"ty":4,"nm":"Слой 1","sr":1,"ks":{"p":{"a":0,"k":[248.135,67.875,0]}},"ao":0,"shapes":[{"ty":"gr","it":[{"ind":0,"ty":"sh","ks":{"a":0,"k":{"i":[[0,0],[-29.067,0.4],[-14.317,-25.762]],"o":[[9.79,-21.241],[26.199,-0.361],[0,0]],"v":[[-66.686,13.214],[-0.825,-14.272],[66.686,14.298]],"c":true}},"nm":"Path 1","hd":false},{"ty":"st","c":{"a":0,"k":[0.68235296011,0.380392163992,0.376470595598,1]},"o":{"a":0,"k":100},"w":{"a":0,"k":8},"lc":1,"lj":1,"ml":10,"bm":0,"nm":"Stroke 1","hd":false},{"ty":"fl","c":{"a":0,"k":[0.807843148708,0.43137255311,0.43137255311,1]},"o":{"a":0,"k":100},"r":1,"bm":0,"nm":"Fill 1","hd":false},{"ty":"tr","p":{"a":0,"k":[0,0]},"a":{"a":0,"k":[0,0]},"s":{"a":0,"k":[100,100]},"r":{"a":0,"k":0},"o":{"a":0,"k":100},"sk":{"a":0,"k":0},"sa":{"a":0,"k":0},"nm":"Transform"}],"nm":"Group 1","bm":0,"hd":false}],"ip":0,"op":1,"st":0,"bm":0}]}