{"tgs":1,"v":"5.5.2","fr":60,"ip":0,"op":1,"w":512,"h":512,"nm":"LADDER","ddd":0,"assets":[],"layers":[{"ddd":0,"ind":1,"ty":4,"nm":"LADDER","sr":1,"ks":{"p":{"a":0,"k":[257,257.125,0]},"a":{"a":0,"k":[257,257.125,0]}},"ao":0,"shapes":[{"ty":"gr","it":[{"ind":0,"ty":"sh","ks":{"a":0,"k":{"i":[[0.615,-1.065],[-0.615,1.065],[-1.065,-0.615]],"o":[[-0.615,1.065],[0.615,-1.065],[1.065,0.615]],"v":[[1.812,1.529],[-2.044,-0.697],[0.997,-1.512]],"c":true}},"nm":"Path 1","hd":false},{"ty":"fl","c":{"a":0,"k":[0.886274516582,0.886274516582,0.886274516582,1]},"o":{"a":0,"k":100},"r":1,"bm":0,"nm":"Fill 1","hd":false},{"ty":"tr","p":{"a":0,"k":[367.558,279.769]},"a":{"a":0,"k":[0,0]},"s":{"a":0,"k":[100,100]},"r":{"a":0,"k":0},"o":{"a":0,"k":100},"sk":{"a":0,"k":0},"sa":{"a":0,"k":0},"nm":"Transform"}],"nm":"Group 1","bm":0,"hd":false},{"ty":"gr","it":[{"ind":0,"ty":"sh","ks":{"a":0,"k":{"i":[[0,-1.858],[1.858,0],[0,1.858],[-1.858,0]],"o":[[0,1.858],[-1.858,0],[0,-1.858],[1.858,0]],"v":[[3.363,0],[0,3.363],[-3.363,0],[0,-3.363]],"c":true}},"nm":"Path 1","hd":false},{"ty":"fl","c":{"a":0,"k":[0.392156869173,0.321568638086,0.305882364511,1]},"o":{"a":0,"k":100},"r":1,"bm":0,"nm":"Fill 1","hd":false},{"ty":"tr","p":{"a":0,"k":[367.405,281.012]},"a":{"a":0,"k":[0,0]},"s":{"a":0,"k":[100,100]},"r":{"a":0,"k":0},"o":{"a":0,"k":100},"sk":{"a":0,"k":0},"sa":{"a":0,"k":0},"nm":"Transform"}],"nm":"Group 2","bm":0,"hd":false},{"ty":"gr","it":[{"ind":0,"ty":"sh","ks":{"a":0,"k":{"i":[[0.615,-1.065],[-0.615,1.065],[-1.065,-0.615]],"o":[[-0.615,1.065],[0.615,-1.065],[1.065,0.615]],"v":[[1.812,1.529],[-2.044,-0.697],[0.997,-1.512]],"c":true}},"nm":"Path 1","hd":false},{"ty":"fl","c":{"a":0,"k":[0.886274516582,0.886274516582,0.886274516582,1]},"o":{"a":0,"k":100},"r":1,"bm":0,"nm":"Fill 1","hd":false},{"ty":"tr","p":{"a":0,"k":[312.454,280.998]},"a":{"a":0,"k":[0,0]},"s":{"a":0,"k":[100,100]},"r":{"a":0,"k":0},"o":{"a":0,"k":100},"sk":{"a":0,"k":0},"sa":{"a":0,"k":0},"nm":"Transform"}],"nm":"Group 3","bm":0,"hd":false},{"ty":"gr","it":[{"ind":0,"ty":"sh","ks":{"a":0,"k":{"i":[[0,-1.858],[1.858,0],[0,1.858],[-1.858,0]],"o":[[0,1.858],[-1.858,0],[0,-1.858],[1.858,0]],"v":[[3.363,0],[0,3.363],[-3.363,0],[0,-3.363]],"c":true}},"nm":"Path 1","hd":false},{"ty":"fl","c":{"a":0,"k":[0.392156869173,0.321568638086,0.305882364511,1]},"o":{"a":0,"k":100},"r":1,"bm":0,"nm":"Fill 1","hd":false},{"ty":"tr","p":{"a":0,"k":[311.988,282.178]},"a":{"a":0,"k":[0,0]},"s":{"a":0,"k":[100,100]},"r":{"a":0,"k":0},"o":{"a":0,"k":100},"sk":{"a":0,"k":0},"sa":{"a":0,"k":0},"nm":"Transform"}],"nm":"Group 4","bm":0,"hd":false},{"ty":"gr","it":[{"ind":0,"ty":"sh","ks":{"a":0,"k":{"i":[[0.615,-1.065],[-0.615,1.065],[-1.065,-0.615]],"o":[[-0.615,1.065],[0.615,-1.065],[1.065,0.615]],"v":[[1.812,1.529],[-2.044,-0.697],[0.997,-1.512]],"c":true}},"nm":"Path 1","hd":false},{"ty":"fl","c":{"a":0,"k":[0.886274516582,0.886274516582,0.886274516582,1]},"o":{"a":0,"k":100},"r":1,"bm":0,"nm":"Fill 1","hd":false},{"ty":"tr","p":{"a":0,"k":[257.058,272.769]},"a":{"a":0,"k":[0,0]},"s":{"a":0,"k":[100,100]},"r":{"a":0,"k":0},"o":{"a":0,"k":100},"sk":{"a":0,"k":0},"sa":{"a":0,"k":0},"nm":"Transform"}],"nm":"Group 5","bm":0,"hd":false},{"ty":"gr","it":[{"ind":0,"ty":"sh","ks":{"a":0,"k":{"i":[[0,-1.858],[1.858,0],[0,1.858],[-1.858,0]],"o":[[0,1.858],[-1.858,0],[0,-1.858],[1.858,0]],"v":[[3.363,0],[0,3.363],[-3.363,0],[0,-3.363]],"c":true}},"nm":"Path 1","hd":false},{"ty":"fl","c":{"a":0,"k":[0.392156869173,0.321568638086,0.305882364511,1]},"o":{"a":0,"k":100},"r":1,"bm":0,"nm":"Fill 1","hd":false},{"ty":"tr","p":{"a":0,"k":[256.905,274.012]},"a":{"a":0,"k":[0,0]},"s":{"a":0,"k":[100,100]},"r":{"a":0,"k":0},"o":{"a":0,"k":100},"sk":{"a":0,"k":0},"sa":{"a":0,"k":0},"nm":"Transform"}],"nm":"Group 6","bm":0,"hd":false},{"ty":"gr","it":[{"ind":0,"ty":"sh","ks":{"a":0,"k":{"i":[[0,-1.625],[0,0],[-0.75,2],[0,0]],"o":[[0,1.625],[0,0],[0.75,-2],[0,0]],"v":[[56.004,2.887],[-0.496,4.387],[-55.996,-4.113],[-0.746,3.387]],"c":true}},"nm":"Path 1","hd":false},{"ty":"st","c":{"a":0,"k":[0.54509806633,0.525490224361,0.509803950787,1]},"o":{"a":0,"k":100},"w":{"a":0,"k":8},"lc":2,"lj":2,"bm":0,"nm":"Stroke 1","hd":false},{"ty":"tr","p":{"a":0,"k":[311.996,278.113]},"a":{"a":0,"k":[0,0]},"s":{"a":0,"k":[100,100]},"r":{"a":0,"k":0},"o":{"a":0,"k":100},"sk":{"a":0,"k":0},"sa":{"a":0,"k":0},"nm":"Transform"}],"nm":"Group 7","bm":0,"hd":false},{"ty":"gr","it":[{"ind":0,"ty":"sh","ks":{"a":0,"k":{"i":[[0,0],[0,0]],"o":[[0,0],[0,0]],"v":[[-54.833,9],[54.833,-9]],"c":false}},"nm":"Path 1","hd":false},{"ty":"st","c":{"a":0,"k":[0.35686275363,0.247058823705,0.156862750649,1]},"o":{"a":0,"k":100},"w":{"a":0,"k":6},"lc":2,"lj":2,"bm":0,"nm":"Stroke 1","hd":false},{"ty":"tr","p":{"a":0,"k":[242.417,68.25]},"a":{"a":0,"k":[0,0]},"s":{"a":0,"k":[100,100]},"r":{"a":0,"k":0},"o":{"a":0,"k":100},"sk":{"a":0,"k":0},"sa":{"a":0,"k":0},"nm":"Transform"}],"nm":"Group 8","bm":0,"hd":false},{"ty":"gr","it":[{"ind":0,"ty":"sh","ks":{"a":0,"k":{"i":[[0,0],[0,0],[0,0]],"o":[[0,0],[0,0],[0,0]],"v":[[-20.25,-11.875],[20.25,-4.875],[20.25,11.875]],"c":false}},"nm":"Path 1","hd":false},{"ty":"st","c":{"a":0,"k":[0.509803950787,0.349019616842,0.239215686917,1]},"o":{"a":0,"k":100},"w":{"a":0,"k":6},"lc":2,"lj":2,"bm":0,"nm":"Stroke 1","hd":false},{"ty":"tr","p":{"a":0,"k":[317.5,71.125]},"a":{"a":0,"k":[0,0]},"s":{"a":0,"k":[100,100]},"r":{"a":0,"k":0},"o":{"a":0,"k":100},"sk":{"a":0,"k":0},"sa":{"a":0,"k":0},"nm":"Transform"}],"nm":"Group 9","bm":0,"hd":false},{"ty":"gr","it":[{"ind":0,"ty":"sh","ks":{"a":0,"k":{"i":[[0,0],[0,0],[0,0],[0,0]],"o":[[0,0],[0,0],[0,0],[0,0]],"v":[[20.25,11.875],[-20.25,4.875],[-20.25,-11.875],[20.25,-4.875]],"c":true}},"nm":"Path 1","hd":false},{"ty":"st","c":{"a":0,"k":[0.35686275363,0.247058823705,0.156862750649,1]},"o":{"a":0,"k":100},"w":{"a":0,"k":6},"lc":2,"lj":2,"bm":0,"nm":"Stroke 1","hd":false},{"ty":"tr","p":{"a":0,"k":[317.5,71.125]},"a":{"a":0,"k":[0,0]},"s":{"a":0,"k":[100,100]},"r":{"a":0,"k":0},"o":{"a":0,"k":100},"sk":{"a":0,"k":0},"sa":{"a":0,"k":0},"nm":"Transform"}],"nm":"Group 10","bm":0,"hd":false},{"ty":"gr","it":[{"ind":0,"ty":"sh","ks":{"a":0,"k":{"i":[[0,0],[0,0],[0,0],[0,0],[0,0]],"o":[[0,0],[0,0],[0,0],[0,0],[0,0]],"v":[[54.667,-0.625],[54.667,-17.375],[-54.833,0.625],[-54.833,17.375],[54.833,-0.625]],"c":false}},"nm":"Path 1","hd":false},{"ty":"st","c":{"a":0,"k":[0.266666680574,0.192156866193,0.1254902035,1]},"o":{"a":0,"k":100},"w":{"a":0,"k":6},"lc":2,"lj":2,"bm":0,"nm":"Stroke 1","hd":false},{"ty":"tr","p":{"a":0,"k":[242.417,76.625]},"a":{"a":0,"k":[0,0]},"s":{"a":0,"k":[100,100]},"r":{"a":0,"k":0},"o":{"a":0,"k":100},"sk":{"a":0,"k":0},"sa":{"a":0,"k":0},"nm":"Transform"}],"nm":"Group 11","bm":0,"hd":false},{"ty":"gr","it":[{"ind":0,"ty":"sh","ks":{"a":0,"k":{"i":[[0,0],[0,0],[0,0],[0,0]],"o":[[0,0],[0,0],[0,0],[0,0]],"v":[[54.875,-1.417],[-54.875,16.583],[-54.625,1.417],[54.875,-16.583]],"c":true}},"nm":"Path 1","hd":false},{"ty":"gf","o":{"a":0,"k":100},"r":1,"bm":0,"g":{"p":3,"k":{"a":0,"k":[0,0.522,0.424,0.286,0.345,0.514,0.382,0.231,1,0.506,0.341,0.176]}},"s":{"a":0,"k":[-55.208,-0.833]},"e":{"a":0,"k":[54.542,-0.833]},"t":1,"nm":"Gradient Fill 1","hd":false},{"ty":"tr","p":{"a":0,"k":[242.208,75.833]},"a":{"a":0,"k":[0,0]},"s":{"a":0,"k":[100,100]},"r":{"a":0,"k":0},"o":{"a":0,"k":100},"sk":{"a":0,"k":0},"sa":{"a":0,"k":0},"nm":"Transform"}],"nm":"Group 12","bm":0,"hd":false},{"ty":"gr","it":[{"ind":0,"ty":"sh","ks":{"a":0,"k":{"i":[[0,0],[0,0],[0,0],[0,0]],"o":[[0,0],[0,0],[0,0],[0,0]],"v":[[20.25,11.875],[-20.25,4.875],[-20.25,-11.875],[20.25,-4.875]],"c":true}},"nm":"Path 1","hd":false},{"ty":"gf","o":{"a":0,"k":100},"r":1,"bm":0,"g":{"p":3,"k":{"a":0,"k":[0,1,0.776,0.573,0.345,0.98,0.747,0.504,1,0.961,0.718,0.435]}},"s":{"a":0,"k":[-14.5,-7.125]},"e":{"a":0,"k":[16.667,7.042]},"t":1,"nm":"Gradient Fill 1","hd":false},{"ty":"tr","p":{"a":0,"k":[317.5,71.125]},"a":{"a":0,"k":[0,0]},"s":{"a":0,"k":[100,100]},"r":{"a":0,"k":0},"o":{"a":0,"k":100},"sk":{"a":0,"k":0},"sa":{"a":0,"k":0},"nm":"Transform"}],"nm":"Group 13","bm":0,"hd":false},{"ty":"gr","it":[{"ind":0,"ty":"sh","ks":{"a":0,"k":{"i":[[0,0],[-13.608,-0.778],[-0.173,7.397]],"o":[[-0.605,6.886],[9.295,2.775],[0,0]],"v":[[-15.783,-7.045],[1.134,6.038],[15.842,-1.67]],"c":true}},"nm":"Path 1","hd":false},{"ty":"st","c":{"a":0,"k":[0.309803932905,0.270588248968,0.286274522543,1]},"o":{"a":0,"k":100},"w":{"a":0,"k":6},"lc":2,"lj":2,"bm":0,"nm":"Stroke 1","hd":false},{"ty":"tr","p":{"a":0,"k":[313.949,85.545]},"a":{"a":0,"k":[0,0]},"s":{"a":0,"k":[100,100]},"r":{"a":0,"k":0},"o":{"a":0,"k":100},"sk":{"a":0,"k":0},"sa":{"a":0,"k":0},"nm":"Transform"}],"nm":"Group 14","bm":0,"hd":false},{"ty":"gr","it":[{"ind":0,"ty":"sh","ks":{"a":0,"k":{"i":[[0,0],[-13.608,-0.778],[-0.173,7.397]],"o":[[-0.605,6.886],[3.792,-3.583],[0,0]],"v":[[-10.2,-6.542],[6.717,6.542],[10.259,-4.042]],"c":true}},"nm":"Path 1","hd":false},{"ty":"fl","c":{"a":0,"k":[0.521568655968,0.482352942228,0.435294121504,1]},"o":{"a":0,"k":100},"r":1,"bm":0,"nm":"Fill 1","hd":false},{"ty":"tr","p":{"a":0,"k":[308.366,85.042]},"a":{"a":0,"k":[0,0]},"s":{"a":0,"k":[100,100]},"r":{"a":0,"k":0},"o":{"a":0,"k":100},"sk":{"a":0,"k":0},"sa":{"a":0,"k":0},"nm":"Transform"}],"nm":"Group 15","bm":0,"hd":false},{"ty":"gr","it":[{"ind":0,"ty":"sh","ks":{"a":0,"k":{"i":[[0,0],[-13.608,-0.778],[-0.173,7.397]],"o":[[-0.605,6.886],[9.295,2.775],[0,0]],"v":[[-15.783,-7.045],[1.134,6.038],[15.842,-1.67]],"c":true}},"nm":"Path 1","hd":false},{"ty":"fl","c":{"a":0,"k":[0.376470595598,0.376470595598,0.376470595598,1]},"o":{"a":0,"k":100},"r":1,"bm":0,"nm":"Fill 1","hd":false},{"ty":"tr","p":{"a":0,"k":[313.949,85.545]},"a":{"a":0,"k":[0,0]},"s":{"a":0,"k":[100,100]},"r":{"a":0,"k":0},"o":{"a":0,"k":100},"sk":{"a":0,"k":0},"sa":{"a":0,"k":0},"nm":"Transform"}],"nm":"Group 16","bm":0,"hd":false},{"ty":"gr","it":[{"ind":0,"ty":"sh","ks":{"a":0,"k":{"i":[[0,0],[0,0],[0,0],[0,0]],"o":[[0,0],[0,0],[0,0],[0,0]],"v":[[-54.547,186.219],[-44.422,186.219],[54.547,-186.219],[44.37,-184.615]],"c":true}},"nm":"Path 1","hd":false},{"ty":"st","c":{"a":0,"k":[0.35686275363,0.247058823705,0.156862750649,1]},"o":{"a":0,"k":100},"w":{"a":0,"k":6},"lc":2,"lj":2,"bm":0,"nm":"Stroke 1","hd":false},{"ty":"tr","p":{"a":0,"k":[244.047,267.781]},"a":{"a":0,"k":[0,0]},"s":{"a":0,"k":[100,100]},"r":{"a":0,"k":0},"o":{"a":0,"k":100},"sk":{"a":0,"k":0},"sa":{"a":0,"k":0},"nm":"Transform"}],"nm":"Group 17","bm":0,"hd":false},{"ty":"gr","it":[{"ind":0,"ty":"sh","ks":{"a":0,"k":{"i":[[0,0],[0,0],[0,0],[0,0]],"o":[[0,0],[0,0],[0,0],[0,0]],"v":[[-57.594,186.219],[-40.156,186.219],[57.594,-183.406],[41.438,-186.219]],"c":true}},"nm":"Path 1","hd":false},{"ty":"st","c":{"a":0,"k":[0.509803950787,0.349019616842,0.239215686917,1]},"o":{"a":0,"k":100},"w":{"a":0,"k":6},"lc":2,"lj":2,"bm":0,"nm":"Stroke 1","hd":false},{"ty":"tr","p":{"a":0,"k":[257.156,267.781]},"a":{"a":0,"k":[0,0]},"s":{"a":0,"k":[100,100]},"r":{"a":0,"k":0},"o":{"a":0,"k":100},"sk":{"a":0,"k":0},"sa":{"a":0,"k":0},"nm":"Transform"}],"nm":"Group 18","bm":0,"hd":false},{"ty":"gr","it":[{"ind":0,"ty":"sh","ks":{"a":0,"k":{"i":[[0,0],[0,0]],"o":[[0,0],[0,0]],"v":[[-49.438,186.25],[49.438,-186.25]],"c":false}},"nm":"Path 1","hd":false},{"ty":"st","c":{"a":0,"k":[1,0.874509811401,0.709803938866,1]},"o":{"a":0,"k":100},"w":{"a":0,"k":6},"lc":2,"lj":2,"bm":0,"nm":"Stroke 1","hd":false},{"ty":"tr","p":{"a":0,"k":[253.062,267.75]},"a":{"a":0,"k":[0,0]},"s":{"a":0,"k":[100,100]},"r":{"a":0,"k":0},"o":{"a":0,"k":100},"sk":{"a":0,"k":0},"sa":{"a":0,"k":0},"nm":"Transform"}],"nm":"Group 19","bm":0,"hd":false},{"ty":"gr","it":[{"ind":0,"ty":"sh","ks":{"a":0,"k":{"i":[[0,0],[0,0],[0,0],[0,0]],"o":[[0,0],[0,0],[0,0],[0,0]],"v":[[-53.297,186.219],[-45.672,186.219],[53.297,-186.219],[45.62,-184.615]],"c":true}},"nm":"Path 1","hd":false},{"ty":"gf","o":{"a":0,"k":100},"r":1,"bm":0,"g":{"p":3,"k":{"a":0,"k":[0,0.51,0.408,0.278,0.345,0.51,0.39,0.267,1,0.51,0.373,0.255]}},"s":{"a":0,"k":[-48.797,171.219]},"e":{"a":0,"k":[51.203,-180.781]},"t":1,"nm":"Gradient Fill 1","hd":false},{"ty":"tr","p":{"a":0,"k":[242.797,267.781]},"a":{"a":0,"k":[0,0]},"s":{"a":0,"k":[100,100]},"r":{"a":0,"k":0},"o":{"a":0,"k":100},"sk":{"a":0,"k":0},"sa":{"a":0,"k":0},"nm":"Transform"}],"nm":"Group 20","bm":0,"hd":false},{"ty":"gr","it":[{"ind":0,"ty":"sh","ks":{"a":0,"k":{"i":[[0,0],[0,0],[0,0],[0,0]],"o":[[0,0],[0,0],[0,0],[0,0]],"v":[[-58.625,186.25],[-39.125,186.25],[58.625,-183.375],[40.25,-186.25]],"c":true}},"nm":"Path 1","hd":false},{"ty":"gf","o":{"a":0,"k":100},"r":1,"bm":0,"g":{"p":3,"k":{"a":0,"k":[0,1,0.776,0.573,0.345,0.98,0.747,0.504,1,0.961,0.718,0.435]}},"s":{"a":0,"k":[6.875,3.25]},"e":{"a":0,"k":[-10.625,-1.25]},"t":1,"nm":"Gradient Fill 1","hd":false},{"ty":"tr","p":{"a":0,"k":[256.125,267.75]},"a":{"a":0,"k":[0,0]},"s":{"a":0,"k":[100,100]},"r":{"a":0,"k":0},"o":{"a":0,"k":100},"sk":{"a":0,"k":0},"sa":{"a":0,"k":0},"nm":"Transform"}],"nm":"Group 21","bm":0,"hd":false},{"ty":"gr","it":[{"ind":0,"ty":"sh","ks":{"a":0,"k":{"i":[[0,0],[0,0]],"o":[[0,0],[0,0]],"v":[[-40.125,2],[40.125,-2]],"c":false}},"nm":"Path 1","hd":false},{"ty":"st","c":{"a":0,"k":[0.35686275363,0.247058823705,0.156862750649,1]},"o":{"a":0,"k":100},"w":{"a":0,"k":6},"lc":2,"lj":2,"bm":0,"nm":"Stroke 1","hd":false},{"ty":"tr","p":{"a":0,"k":[176.125,308.75]},"a":{"a":0,"k":[0,0]},"s":{"a":0,"k":[100,100]},"r":{"a":0,"k":0},"o":{"a":0,"k":100},"sk":{"a":0,"k":0},"sa":{"a":0,"k":0},"nm":"Transform"}],"nm":"Group 22","bm":0,"hd":false},{"ty":"gr","it":[{"ind":0,"ty":"sh","ks":{"a":0,"k":{"i":[[0,0],[0,0]],"o":[[0,0],[0,0]],"v":[[-40.125,1],[40.125,-1]],"c":false}},"nm":"Path 1","hd":false},{"ty":"st","c":{"a":0,"k":[0.35686275363,0.247058823705,0.156862750649,1]},"o":{"a":0,"k":100},"w":{"a":0,"k":6},"lc":2,"lj":2,"bm":0,"nm":"Stroke 1","hd":false},{"ty":"tr","p":{"a":0,"k":[149.125,397.75]},"a":{"a":0,"k":[0,0]},"s":{"a":0,"k":[100,100]},"r":{"a":0,"k":0},"o":{"a":0,"k":100},"sk":{"a":0,"k":0},"sa":{"a":0,"k":0},"nm":"Transform"}],"nm":"Group 23","bm":0,"hd":false},{"ty":"gr","it":[{"ind":0,"ty":"sh","ks":{"a":0,"k":{"i":[[0,0],[0,0]],"o":[[0,0],[0,0]],"v":[[-40.125,3],[40.125,-3]],"c":false}},"nm":"Path 1","hd":false},{"ty":"st","c":{"a":0,"k":[0.35686275363,0.247058823705,0.156862750649,1]},"o":{"a":0,"k":100},"w":{"a":0,"k":6},"lc":2,"lj":2,"bm":0,"nm":"Stroke 1","hd":false},{"ty":"tr","p":{"a":0,"k":[199.125,221.75]},"a":{"a":0,"k":[0,0]},"s":{"a":0,"k":[100,100]},"r":{"a":0,"k":0},"o":{"a":0,"k":100},"sk":{"a":0,"k":0},"sa":{"a":0,"k":0},"nm":"Transform"}],"nm":"Group 24","bm":0,"hd":false},{"ty":"gr","it":[{"ind":0,"ty":"sh","ks":{"a":0,"k":{"i":[[0,0],[0,0],[0,0],[0,0]],"o":[[0,0],[0,0],[0,0],[0,0]],"v":[[-13.375,9.75],[13.375,9.5],[13.375,-9.5],[-13.375,-9.75]],"c":true}},"nm":"Path 1","hd":false},{"ty":"st","c":{"a":0,"k":[0.35686275363,0.247058823705,0.156862750649,1]},"o":{"a":0,"k":100},"w":{"a":0,"k":6},"lc":2,"lj":2,"bm":0,"nm":"Stroke 1","hd":false},{"ty":"tr","p":{"a":0,"k":[200.625,406.5]},"a":{"a":0,"k":[0,0]},"s":{"a":0,"k":[100,100]},"r":{"a":0,"k":0},"o":{"a":0,"k":100},"sk":{"a":0,"k":0},"sa":{"a":0,"k":0},"nm":"Transform"}],"nm":"Group 25","bm":0,"hd":false},{"ty":"gr","it":[{"ind":0,"ty":"sh","ks":{"a":0,"k":{"i":[[0,0],[0,0],[0,0],[0,0]],"o":[[0,0],[0,0],[0,0],[0,0]],"v":[[-13.375,-9.75],[13.375,-9.5],[13.375,9.5],[-13.375,9.75]],"c":false}},"nm":"Path 1","hd":false},{"ty":"fl","c":{"a":0,"k":[0.741176486015,0.584313750267,0.443137258291,1]},"o":{"a":0,"k":100},"r":1,"bm":0,"nm":"Fill 1","hd":false},{"ty":"tr","p":{"a":0,"k":[200.625,406.5]},"a":{"a":0,"k":[0,0]},"s":{"a":0,"k":[100,100]},"r":{"a":0,"k":0},"o":{"a":0,"k":100},"sk":{"a":0,"k":0},"sa":{"a":0,"k":0},"nm":"Transform"}],"nm":"Group 26","bm":0,"hd":false},{"ty":"gr","it":[{"ind":0,"ty":"sh","ks":{"a":0,"k":{"i":[[0,0],[0,0],[0,0],[0,0]],"o":[[0,0],[0,0],[0,0],[0,0]],"v":[[40.125,9.25],[-40.125,10.25],[-40.125,-8.25],[40.125,-10.25]],"c":true}},"nm":"Path 1","hd":false},{"ty":"st","c":{"a":0,"k":[0.266666680574,0.192156866193,0.1254902035,1]},"o":{"a":0,"k":100},"w":{"a":0,"k":6},"lc":2,"lj":2,"bm":0,"nm":"Stroke 1","hd":false},{"ty":"tr","p":{"a":0,"k":[149.125,407]},"a":{"a":0,"k":[0,0]},"s":{"a":0,"k":[100,100]},"r":{"a":0,"k":0},"o":{"a":0,"k":100},"sk":{"a":0,"k":0},"sa":{"a":0,"k":0},"nm":"Transform"}],"nm":"Group 27","bm":0,"hd":false},{"ty":"gr","it":[{"ind":0,"ty":"sh","ks":{"a":0,"k":{"i":[[0,0],[0,0],[0,0],[0,0]],"o":[[0,0],[0,0],[0,0],[0,0]],"v":[[40.125,9.25],[-40.125,10.25],[-40.125,-8.25],[40.125,-10.25]],"c":true}},"nm":"Path 1","hd":false},{"ty":"gf","o":{"a":0,"k":100},"r":1,"bm":0,"g":{"p":3,"k":{"a":0,"k":[0,0.522,0.424,0.286,0.345,0.514,0.382,0.231,1,0.506,0.341,0.176]}},"s":{"a":0,"k":[-40.125,0]},"e":{"a":0,"k":[40.125,0]},"t":1,"nm":"Gradient Fill 1","hd":false},{"ty":"tr","p":{"a":0,"k":[149.125,407]},"a":{"a":0,"k":[0,0]},"s":{"a":0,"k":[100,100]},"r":{"a":0,"k":0},"o":{"a":0,"k":100},"sk":{"a":0,"k":0},"sa":{"a":0,"k":0},"nm":"Transform"}],"nm":"Group 28","bm":0,"hd":false},{"ty":"gr","it":[{"ind":0,"ty":"sh","ks":{"a":0,"k":{"i":[[0,0],[0,0],[0,0],[0,0]],"o":[[0,0],[0,0],[0,0],[0,0]],"v":[[-13.375,9.375],[13.375,10.125],[13.375,-7.875],[-13.375,-10.125]],"c":true}},"nm":"Path 1","hd":false},{"ty":"st","c":{"a":0,"k":[0.35686275363,0.247058823705,0.156862750649,1]},"o":{"a":0,"k":100},"w":{"a":0,"k":6},"lc":2,"lj":2,"bm":0,"nm":"Stroke 1","hd":false},{"ty":"tr","p":{"a":0,"k":[227.625,316.875]},"a":{"a":0,"k":[0,0]},"s":{"a":0,"k":[100,100]},"r":{"a":0,"k":0},"o":{"a":0,"k":100},"sk":{"a":0,"k":0},"sa":{"a":0,"k":0},"nm":"Transform"}],"nm":"Group 29","bm":0,"hd":false},{"ty":"gr","it":[{"ind":0,"ty":"sh","ks":{"a":0,"k":{"i":[[0,0],[0,0],[0,0],[0,0]],"o":[[0,0],[0,0],[0,0],[0,0]],"v":[[-13.375,-10.125],[13.375,-7.875],[13.375,10.125],[-13.375,9.375]],"c":false}},"nm":"Path 1","hd":false},{"ty":"fl","c":{"a":0,"k":[0.741176486015,0.584313750267,0.443137258291,1]},"o":{"a":0,"k":100},"r":1,"bm":0,"nm":"Fill 1","hd":false},{"ty":"tr","p":{"a":0,"k":[227.625,316.875]},"a":{"a":0,"k":[0,0]},"s":{"a":0,"k":[100,100]},"r":{"a":0,"k":0},"o":{"a":0,"k":100},"sk":{"a":0,"k":0},"sa":{"a":0,"k":0},"nm":"Transform"}],"nm":"Group 30","bm":0,"hd":false},{"ty":"gr","it":[{"ind":0,"ty":"sh","ks":{"a":0,"k":{"i":[[0,0],[0,0],[0,0]],"o":[[0,0],[0,0],[0,0]],"v":[[-53.5,0.75],[-36.25,1.5],[53.5,-1.5]],"c":false}},"nm":"Path 1","hd":false},{"ty":"st","c":{"a":0,"k":[0.266666680574,0.192156866193,0.1254902035,1]},"o":{"a":0,"k":100},"w":{"a":0,"k":6},"lc":2,"lj":2,"bm":0,"nm":"Stroke 1","hd":false},{"ty":"tr","p":{"a":0,"k":[189.5,328.5]},"a":{"a":0,"k":[0,0]},"s":{"a":0,"k":[100,100]},"r":{"a":0,"k":0},"o":{"a":0,"k":100},"sk":{"a":0,"k":0},"sa":{"a":0,"k":0},"nm":"Transform"}],"nm":"Group 31","bm":0,"hd":false},{"ty":"gr","it":[{"ind":0,"ty":"sh","ks":{"a":0,"k":{"i":[[0,0],[0,0],[0,0],[0,0]],"o":[[0,0],[0,0],[0,0],[0,0]],"v":[[40.125,8.25],[-40.125,11.25],[-40.125,-7.25],[40.125,-11.25]],"c":true}},"nm":"Path 1","hd":false},{"ty":"st","c":{"a":0,"k":[0.266666680574,0.192156866193,0.1254902035,1]},"o":{"a":0,"k":100},"w":{"a":0,"k":6},"lc":2,"lj":2,"bm":0,"nm":"Stroke 1","hd":false},{"ty":"tr","p":{"a":0,"k":[176.125,318]},"a":{"a":0,"k":[0,0]},"s":{"a":0,"k":[100,100]},"r":{"a":0,"k":0},"o":{"a":0,"k":100},"sk":{"a":0,"k":0},"sa":{"a":0,"k":0},"nm":"Transform"}],"nm":"Group 32","bm":0,"hd":false},{"ty":"gr","it":[{"ind":0,"ty":"sh","ks":{"a":0,"k":{"i":[[0,0],[0,0],[0,0],[0,0]],"o":[[0,0],[0,0],[0,0],[0,0]],"v":[[40.125,8.25],[-40.125,11.25],[-40.125,-7.25],[40.125,-11.25]],"c":true}},"nm":"Path 1","hd":false},{"ty":"gf","o":{"a":0,"k":100},"r":1,"bm":0,"g":{"p":3,"k":{"a":0,"k":[0,0.522,0.424,0.286,0.345,0.514,0.382,0.231,1,0.506,0.341,0.176]}},"s":{"a":0,"k":[-40.125,0]},"e":{"a":0,"k":[40.125,0]},"t":1,"nm":"Gradient Fill 1","hd":false},{"ty":"tr","p":{"a":0,"k":[176.125,318]},"a":{"a":0,"k":[0,0]},"s":{"a":0,"k":[100,100]},"r":{"a":0,"k":0},"o":{"a":0,"k":100},"sk":{"a":0,"k":0},"sa":{"a":0,"k":0},"nm":"Transform"}],"nm":"Group 33","bm":0,"hd":false},{"ty":"gr","it":[{"ind":0,"ty":"sh","ks":{"a":0,"k":{"i":[[0,0],[0,0],[0,0],[0,0]],"o":[[0,0],[0,0],[0,0],[0,0]],"v":[[-13.375,-10.125],[13.375,-7.875],[13.375,10.125],[-13.375,9.375]],"c":true}},"nm":"Path 1","hd":false},{"ty":"st","c":{"a":0,"k":[0.35686275363,0.247058823705,0.156862750649,1]},"o":{"a":0,"k":100},"w":{"a":0,"k":6},"lc":2,"lj":2,"bm":0,"nm":"Stroke 1","hd":false},{"ty":"tr","p":{"a":0,"k":[250.625,228.875]},"a":{"a":0,"k":[0,0]},"s":{"a":0,"k":[100,100]},"r":{"a":0,"k":0},"o":{"a":0,"k":100},"sk":{"a":0,"k":0},"sa":{"a":0,"k":0},"nm":"Transform"}],"nm":"Group 34","bm":0,"hd":false},{"ty":"gr","it":[{"ind":0,"ty":"sh","ks":{"a":0,"k":{"i":[[0,0],[0,0],[0,0],[0,0]],"o":[[0,0],[0,0],[0,0],[0,0]],"v":[[-13.375,-10.125],[13.375,-7.875],[13.375,10.125],[-13.375,9.375]],"c":false}},"nm":"Path 1","hd":false},{"ty":"fl","c":{"a":0,"k":[0.741176486015,0.584313750267,0.443137258291,1]},"o":{"a":0,"k":100},"r":1,"bm":0,"nm":"Fill 1","hd":false},{"ty":"tr","p":{"a":0,"k":[250.625,228.875]},"a":{"a":0,"k":[0,0]},"s":{"a":0,"k":[100,100]},"r":{"a":0,"k":0},"o":{"a":0,"k":100},"sk":{"a":0,"k":0},"sa":{"a":0,"k":0},"nm":"Transform"}],"nm":"Group 35","bm":0,"hd":false},{"ty":"gr","it":[{"ind":0,"ty":"sh","ks":{"a":0,"k":{"i":[[0,0],[0,0],[0,0]],"o":[[0,0],[0,0],[0,0]],"v":[[-53.5,1.75],[-36.25,2.5],[53.5,-2.5]],"c":false}},"nm":"Path 1","hd":false},{"ty":"st","c":{"a":0,"k":[0.266666680574,0.192156866193,0.1254902035,1]},"o":{"a":0,"k":100},"w":{"a":0,"k":6},"lc":2,"lj":2,"bm":0,"nm":"Stroke 1","hd":false},{"ty":"tr","p":{"a":0,"k":[212.5,241.5]},"a":{"a":0,"k":[0,0]},"s":{"a":0,"k":[100,100]},"r":{"a":0,"k":0},"o":{"a":0,"k":100},"sk":{"a":0,"k":0},"sa":{"a":0,"k":0},"nm":"Transform"}],"nm":"Group 36","bm":0,"hd":false},{"ty":"gr","it":[{"ind":0,"ty":"sh","ks":{"a":0,"k":{"i":[[0,0],[0,0],[0,0],[0,0]],"o":[[0,0],[0,0],[0,0],[0,0]],"v":[[40.125,7.25],[-40.125,12.25],[-40.125,-6.25],[40.125,-12.25]],"c":true}},"nm":"Path 1","hd":false},{"ty":"st","c":{"a":0,"k":[0.266666680574,0.192156866193,0.1254902035,1]},"o":{"a":0,"k":100},"w":{"a":0,"k":6},"lc":2,"lj":2,"bm":0,"nm":"Stroke 1","hd":false},{"ty":"tr","p":{"a":0,"k":[199.125,231]},"a":{"a":0,"k":[0,0]},"s":{"a":0,"k":[100,100]},"r":{"a":0,"k":0},"o":{"a":0,"k":100},"sk":{"a":0,"k":0},"sa":{"a":0,"k":0},"nm":"Transform"}],"nm":"Group 37","bm":0,"hd":false},{"ty":"gr","it":[{"ind":0,"ty":"sh","ks":{"a":0,"k":{"i":[[0,0],[0,0],[0,0],[0,0]],"o":[[0,0],[0,0],[0,0],[0,0]],"v":[[40.125,7.25],[-40.125,12.25],[-40.125,-6.25],[40.125,-12.25]],"c":true}},"nm":"Path 1","hd":false},{"ty":"gf","o":{"a":0,"k":100},"r":1,"bm":0,"g":{"p":3,"k":{"a":0,"k":[0,0.522,0.424,0.286,0.345,0.514,0.382,0.231,1,0.506,0.341,0.176]}},"s":{"a":0,"k":[-40.125,0]},"e":{"a":0,"k":[40.125,0]},"t":1,"nm":"Gradient Fill 1","hd":false},{"ty":"tr","p":{"a":0,"k":[199.125,231]},"a":{"a":0,"k":[0,0]},"s":{"a":0,"k":[100,100]},"r":{"a":0,"k":0},"o":{"a":0,"k":100},"sk":{"a":0,"k":0},"sa":{"a":0,"k":0},"nm":"Transform"}],"nm":"Group 38","bm":0,"hd":false},{"ty":"gr","it":[{"ind":0,"ty":"sh","ks":{"a":0,"k":{"i":[[0,0],[0,0],[0,0],[0,0],[0,0],[0,0]],"o":[[0,0],[0,0],[0,0],[0,0],[0,0],[0,0]],"v":[[25.698,-9.75],[52.448,-8.5],[52.448,9.5],[25.698,9.75],[25.698,-9.75],[-52.448,0.25]],"c":false}},"nm":"Path 1","hd":false},{"ty":"st","c":{"a":0,"k":[0.35686275363,0.247058823705,0.156862750649,1]},"o":{"a":0,"k":100},"w":{"a":0,"k":6},"lc":2,"lj":2,"bm":0,"nm":"Stroke 1","hd":false},{"ty":"tr","p":{"a":0,"k":[233.552,143.5]},"a":{"a":0,"k":[0,0]},"s":{"a":0,"k":[100,100]},"r":{"a":0,"k":0},"o":{"a":0,"k":100},"sk":{"a":0,"k":0},"sa":{"a":0,"k":0},"nm":"Transform"}],"nm":"Group 39","bm":0,"hd":false},{"ty":"gr","it":[{"ind":0,"ty":"sh","ks":{"a":0,"k":{"i":[[0,0],[0,0],[0,0],[0,0]],"o":[[0,0],[0,0],[0,0],[0,0]],"v":[[-13.375,-9.75],[13.375,-8.5],[13.375,9.5],[-13.375,9.75]],"c":false}},"nm":"Path 1","hd":false},{"ty":"fl","c":{"a":0,"k":[0.741176486015,0.584313750267,0.443137258291,1]},"o":{"a":0,"k":100},"r":1,"bm":0,"nm":"Fill 1","hd":false},{"ty":"tr","p":{"a":0,"k":[272.625,143.5]},"a":{"a":0,"k":[0,0]},"s":{"a":0,"k":[100,100]},"r":{"a":0,"k":0},"o":{"a":0,"k":100},"sk":{"a":0,"k":0},"sa":{"a":0,"k":0},"nm":"Transform"}],"nm":"Group 40","bm":0,"hd":false},{"ty":"gr","it":[{"ind":0,"ty":"sh","ks":{"a":0,"k":{"i":[[0,0],[0,0],[0,0],[0,0]],"o":[[0,0],[0,0],[0,0],[0,0]],"v":[[40.125,5.25],[-40.125,14.25],[-40.125,-4.25],[40.125,-14.25]],"c":true}},"nm":"Path 1","hd":false},{"ty":"st","c":{"a":0,"k":[0.266666680574,0.192156866193,0.1254902035,1]},"o":{"a":0,"k":100},"w":{"a":0,"k":6},"lc":2,"lj":2,"bm":0,"nm":"Stroke 1","hd":false},{"ty":"tr","p":{"a":0,"k":[221.125,148]},"a":{"a":0,"k":[0,0]},"s":{"a":0,"k":[100,100]},"r":{"a":0,"k":0},"o":{"a":0,"k":100},"sk":{"a":0,"k":0},"sa":{"a":0,"k":0},"nm":"Transform"}],"nm":"Group 41","bm":0,"hd":false},{"ty":"gr","it":[{"ind":0,"ty":"sh","ks":{"a":0,"k":{"i":[[0,0],[0,0],[0,0]],"o":[[0,0],[0,0],[0,0]],"v":[[-53.5,4.25],[-36.25,5],[53.5,-5]],"c":false}},"nm":"Path 1","hd":false},{"ty":"st","c":{"a":0,"k":[0.266666680574,0.192156866193,0.1254902035,1]},"o":{"a":0,"k":100},"w":{"a":0,"k":6},"lc":2,"lj":2,"bm":0,"nm":"Stroke 1","hd":false},{"ty":"tr","p":{"a":0,"k":[234.5,158]},"a":{"a":0,"k":[0,0]},"s":{"a":0,"k":[100,100]},"r":{"a":0,"k":0},"o":{"a":0,"k":100},"sk":{"a":0,"k":0},"sa":{"a":0,"k":0},"nm":"Transform"}],"nm":"Group 42","bm":0,"hd":false},{"ty":"gr","it":[{"ind":0,"ty":"sh","ks":{"a":0,"k":{"i":[[0,0],[0,0],[0,0],[0,0]],"o":[[0,0],[0,0],[0,0],[0,0]],"v":[[40.125,5.25],[-40.125,14.25],[-40.125,-4.25],[40.125,-14.25]],"c":true}},"nm":"Path 1","hd":false},{"ty":"gf","o":{"a":0,"k":100},"r":1,"bm":0,"g":{"p":3,"k":{"a":0,"k":[0,0.522,0.424,0.286,0.345,0.514,0.382,0.231,1,0.506,0.341,0.176]}},"s":{"a":0,"k":[-40.125,0]},"e":{"a":0,"k":[40.125,0]},"t":1,"nm":"Gradient Fill 1","hd":false},{"ty":"tr","p":{"a":0,"k":[221.125,148]},"a":{"a":0,"k":[0,0]},"s":{"a":0,"k":[100,100]},"r":{"a":0,"k":0},"o":{"a":0,"k":100},"sk":{"a":0,"k":0},"sa":{"a":0,"k":0},"nm":"Transform"}],"nm":"Group 43","bm":0,"hd":false},{"ty":"gr","it":[{"ind":0,"ty":"sh","ks":{"a":0,"k":{"i":[[0,0],[0,0],[0,0],[0,0]],"o":[[0,0],[0,0],[0,0],[0,0]],"v":[[-17.625,65.833],[17.625,-62.958],[-0.75,-65.833],[-4.708,-52.167]],"c":false}},"nm":"Path 1","hd":false},{"ty":"st","c":{"a":0,"k":[0.266666680574,0.192156866193,0.1254902035,1]},"o":{"a":0,"k":100},"w":{"a":0,"k":6},"lc":2,"lj":2,"bm":0,"nm":"Stroke 1","hd":false},{"ty":"tr","p":{"a":0,"k":[206.125,159.333]},"a":{"a":0,"k":[0,0]},"s":{"a":0,"k":[100,100]},"r":{"a":0,"k":0},"o":{"a":0,"k":100},"sk":{"a":0,"k":0},"sa":{"a":0,"k":0},"nm":"Transform"}],"nm":"Group 44","bm":0,"hd":false},{"ty":"gr","it":[{"ind":0,"ty":"sh","ks":{"a":0,"k":{"i":[[0,0],[0,0],[0,0],[0,0]],"o":[[0,0],[0,0],[0,0],[0,0]],"v":[[-58.625,180.25],[-39.125,180.25],[58.625,-177.375],[40.25,-180.25]],"c":true}},"nm":"Path 1","hd":false},{"ty":"st","c":{"a":0,"k":[0.35686275363,0.247058823705,0.156862750649,1]},"o":{"a":0,"k":100},"w":{"a":0,"k":6},"lc":2,"lj":2,"bm":0,"nm":"Stroke 1","hd":false},{"ty":"tr","p":{"a":0,"k":[165.125,273.75]},"a":{"a":0,"k":[0,0]},"s":{"a":0,"k":[100,100]},"r":{"a":0,"k":0},"o":{"a":0,"k":100},"sk":{"a":0,"k":0},"sa":{"a":0,"k":0},"nm":"Transform"}],"nm":"Group 45","bm":0,"hd":false},{"ty":"gr","it":[{"ind":0,"ty":"sh","ks":{"a":0,"k":{"i":[[0,0],[0,0],[0,0],[0,0]],"o":[[0,0],[0,0],[0,0],[0,0]],"v":[[-53.297,180.219],[-45.672,180.219],[53.297,-180.219],[45.62,-178.615]],"c":true}},"nm":"Path 1","hd":false},{"ty":"st","c":{"a":0,"k":[0.35686275363,0.247058823705,0.156862750649,1]},"o":{"a":0,"k":100},"w":{"a":0,"k":6},"lc":2,"lj":2,"bm":0,"nm":"Stroke 1","hd":false},{"ty":"tr","p":{"a":0,"k":[151.797,273.781]},"a":{"a":0,"k":[0,0]},"s":{"a":0,"k":[100,100]},"r":{"a":0,"k":0},"o":{"a":0,"k":100},"sk":{"a":0,"k":0},"sa":{"a":0,"k":0},"nm":"Transform"}],"nm":"Group 46","bm":0,"hd":false},{"ty":"gr","it":[{"ind":0,"ty":"sh","ks":{"a":0,"k":{"i":[[0,0],[0,0],[0,0],[0,0]],"o":[[0,0],[0,0],[0,0],[0,0]],"v":[[-53.297,180.219],[-45.672,180.219],[53.297,-180.219],[45.62,-178.615]],"c":true}},"nm":"Path 1","hd":false},{"ty":"fl","c":{"a":0,"k":[0.54509806633,0.396078437567,0.227450981736,1]},"o":{"a":0,"k":100},"r":1,"bm":0,"nm":"Fill 1","hd":false},{"ty":"tr","p":{"a":0,"k":[151.797,273.781]},"a":{"a":0,"k":[0,0]},"s":{"a":0,"k":[100,100]},"r":{"a":0,"k":0},"o":{"a":0,"k":100},"sk":{"a":0,"k":0},"sa":{"a":0,"k":0},"nm":"Transform"}],"nm":"Group 47","bm":0,"hd":false},{"ty":"gr","it":[{"ind":0,"ty":"sh","ks":{"a":0,"k":{"i":[[0,0],[0,0],[0,0],[0,0]],"o":[[0,0],[0,0],[0,0],[0,0]],"v":[[-9.5,-19.5],[-11.833,19.5],[0.5,18.5],[11.833,-19.5]],"c":true}},"nm":"Path 1","hd":false},{"ty":"gf","o":{"a":0,"k":100},"r":1,"bm":0,"g":{"p":3,"k":{"a":0,"k":[0,0.494,0.365,0.243,0.345,0.494,0.365,0.243,1,0.494,0.365,0.243,0,0,0.345,0.5,1,1]}},"s":{"a":0,"k":[-10.5,-0.833]},"e":{"a":0,"k":[-4.544,-0.833]},"t":1,"nm":"Gradient Fill 1","hd":false},{"ty":"tr","p":{"a":0,"k":[126.5,433.833]},"a":{"a":0,"k":[0,0]},"s":{"a":0,"k":[100,100]},"r":{"a":0,"k":0},"o":{"a":0,"k":100},"sk":{"a":0,"k":0},"sa":{"a":0,"k":0},"nm":"Transform"}],"nm":"Group 48","bm":0,"hd":false},{"ty":"gr","it":[{"ind":0,"ty":"sh","ks":{"a":0,"k":{"i":[[0,0],[0,0],[0,0],[0,0]],"o":[[0,0],[0,0],[0,0],[0,0]],"v":[[-6.958,-35.625],[-13.208,35.625],[-6.125,35.042],[13.208,-35.292]],"c":true}},"nm":"Path 1","hd":false},{"ty":"gf","o":{"a":0,"k":100},"r":1,"bm":0,"g":{"p":3,"k":{"a":0,"k":[0,0.494,0.365,0.243,0.345,0.494,0.365,0.243,1,0.494,0.365,0.243,0,0,0.345,0.5,1,1]}},"s":{"a":0,"k":[-11.458,-0.625]},"e":{"a":0,"k":[-4.81,-0.625]},"t":1,"nm":"Gradient Fill 1","hd":false},{"ty":"tr","p":{"a":0,"k":[147.458,365.625]},"a":{"a":0,"k":[0,0]},"s":{"a":0,"k":[100,100]},"r":{"a":0,"k":0},"o":{"a":0,"k":100},"sk":{"a":0,"k":0},"sa":{"a":0,"k":0},"nm":"Transform"}],"nm":"Group 49","bm":0,"hd":false},{"ty":"gr","it":[{"ind":0,"ty":"sh","ks":{"a":0,"k":{"i":[[0,0],[0,0],[0,0],[0,0]],"o":[[0,0],[0,0],[0,0],[0,0]],"v":[[-6.75,-34.833],[-13.25,35.167],[-6.083,35.167],[13.25,-35.167]],"c":true}},"nm":"Path 1","hd":false},{"ty":"gf","o":{"a":0,"k":100},"r":1,"bm":0,"g":{"p":3,"k":{"a":0,"k":[0,0.494,0.365,0.243,0.345,0.494,0.365,0.243,1,0.494,0.365,0.243,0,0,0.345,0.5,1,1]}},"s":{"a":0,"k":[-11.5,-0.833]},"e":{"a":0,"k":[-4.831,-0.833]},"t":1,"nm":"Gradient Fill 1","hd":false},{"ty":"tr","p":{"a":0,"k":[171.5,278.833]},"a":{"a":0,"k":[0,0]},"s":{"a":0,"k":[100,100]},"r":{"a":0,"k":0},"o":{"a":0,"k":100},"sk":{"a":0,"k":0},"sa":{"a":0,"k":0},"nm":"Transform"}],"nm":"Group 50","bm":0,"hd":false},{"ty":"gr","it":[{"ind":0,"ty":"sh","ks":{"a":0,"k":{"i":[[0,0],[0,0],[0,0],[0,0]],"o":[[0,0],[0,0],[0,0],[0,0]],"v":[[-8.75,-31.583],[-12.583,28.25],[-6.75,31.583],[12.583,-31.583]],"c":true}},"nm":"Path 1","hd":false},{"ty":"gf","o":{"a":0,"k":100},"r":1,"bm":0,"g":{"p":3,"k":{"a":0,"k":[0,0.494,0.365,0.243,0.345,0.494,0.365,0.243,1,0.494,0.365,0.243,0,0,0.345,0.5,1,1]}},"s":{"a":0,"k":[-11.083,-0.25]},"e":{"a":0,"k":[-4.749,-0.25]},"t":1,"nm":"Gradient Fill 1","hd":false},{"ty":"tr","p":{"a":0,"k":[195.083,195.25]},"a":{"a":0,"k":[0,0]},"s":{"a":0,"k":[100,100]},"r":{"a":0,"k":0},"o":{"a":0,"k":100},"sk":{"a":0,"k":0},"sa":{"a":0,"k":0},"nm":"Transform"}],"nm":"Group 51","bm":0,"hd":false},{"ty":"gr","it":[{"ind":0,"ty":"sh","ks":{"a":0,"k":{"i":[[0,0],[0,0],[0,0],[0,0]],"o":[[0,0],[0,0],[0,0],[0,0]],"v":[[3.375,-42.958],[-20.875,41.958],[-2.042,42.958],[20.875,-36.208]],"c":true}},"nm":"Path 1","hd":false},{"ty":"gf","o":{"a":0,"k":100},"r":1,"bm":0,"g":{"p":5,"k":{"a":0,"k":[0,0.494,0.365,0.243,0.223,0.494,0.365,0.243,0.514,0.494,0.365,0.243,0.863,0.494,0.365,0.243,1,0.494,0.365,0.243,0,0,0.223,0.5,0.514,1,0.863,0.528,1,0.057]}},"s":{"a":0,"k":[12.625,-31.042]},"e":{"a":0,"k":[-13.275,33.903]},"t":1,"nm":"Gradient Fill 1","hd":false},{"ty":"tr","p":{"a":0,"k":[127.375,412.042]},"a":{"a":0,"k":[0,0]},"s":{"a":0,"k":[100,100]},"r":{"a":0,"k":0},"o":{"a":0,"k":100},"sk":{"a":0,"k":0},"sa":{"a":0,"k":0},"nm":"Transform"}],"nm":"Group 52","bm":0,"hd":false},{"ty":"gr","it":[{"ind":0,"ty":"sh","ks":{"a":0,"k":{"i":[[0,0],[0,0],[0,0],[0,0]],"o":[[0,0],[0,0],[0,0],[0,0]],"v":[[-3.5,-19.875],[-14,18.125],[3,19.875],[14,-13.125]],"c":true}},"nm":"Path 1","hd":false},{"ty":"gf","o":{"a":0,"k":100},"r":1,"bm":0,"g":{"p":3,"k":{"a":0,"k":[0,0.494,0.365,0.243,0.345,0.494,0.365,0.243,1,0.494,0.365,0.243,0,0,0.345,0.5,1,1]}},"s":{"a":0,"k":[4.75,-12.958]},"e":{"a":0,"k":[-7.945,18.874]},"t":1,"nm":"Gradient Fill 1","hd":false},{"ty":"tr","p":{"a":0,"k":[157.25,302.958]},"a":{"a":0,"k":[0,0]},"s":{"a":0,"k":[100,100]},"r":{"a":0,"k":0},"o":{"a":0,"k":100},"sk":{"a":0,"k":0},"sa":{"a":0,"k":0},"nm":"Transform"}],"nm":"Group 53","bm":0,"hd":false},{"ty":"gr","it":[{"ind":0,"ty":"sh","ks":{"a":0,"k":{"i":[[0,0],[0,0],[0,0],[0,0]],"o":[[0,0],[0,0],[0,0],[0,0]],"v":[[-3.5,-19.875],[-14,18.125],[3,19.875],[14,-13.125]],"c":true}},"nm":"Path 1","hd":false},{"ty":"gf","o":{"a":0,"k":100},"r":1,"bm":0,"g":{"p":3,"k":{"a":0,"k":[0,0.494,0.365,0.243,0.345,0.494,0.365,0.243,1,0.494,0.365,0.243,0,0,0.345,0.5,1,1]}},"s":{"a":0,"k":[4.083,-13.292]},"e":{"a":0,"k":[-8.612,18.54]},"t":1,"nm":"Gradient Fill 1","hd":false},{"ty":"tr","p":{"a":0,"k":[180.917,216.292]},"a":{"a":0,"k":[0,0]},"s":{"a":0,"k":[100,100]},"r":{"a":0,"k":0},"o":{"a":0,"k":100},"sk":{"a":0,"k":0},"sa":{"a":0,"k":0},"nm":"Transform"}],"nm":"Group 54","bm":0,"hd":false},{"ty":"gr","it":[{"ind":0,"ty":"sh","ks":{"a":0,"k":{"i":[[0,0],[0,0],[0,0],[0,0]],"o":[[0,0],[0,0],[0,0],[0,0]],"v":[[-3.5,-19.875],[-14,18.125],[3,19.875],[14,-13.125]],"c":true}},"nm":"Path 1","hd":false},{"ty":"gf","o":{"a":0,"k":100},"r":1,"bm":0,"g":{"p":3,"k":{"a":0,"k":[0,0.494,0.365,0.243,0.345,0.494,0.365,0.243,1,0.494,0.365,0.243,0,0,0.345,0.5,1,1]}},"s":{"a":0,"k":[4.75,-13.625]},"e":{"a":0,"k":[-7.945,18.207]},"t":1,"nm":"Gradient Fill 1","hd":false},{"ty":"tr","p":{"a":0,"k":[203.25,136.625]},"a":{"a":0,"k":[0,0]},"s":{"a":0,"k":[100,100]},"r":{"a":0,"k":0},"o":{"a":0,"k":100},"sk":{"a":0,"k":0},"sa":{"a":0,"k":0},"nm":"Transform"}],"nm":"Group 55","bm":0,"hd":false},{"ty":"gr","it":[{"ind":0,"ty":"sh","ks":{"a":0,"k":{"i":[[0,0],[0,0],[0,0],[0,0]],"o":[[0,0],[0,0],[0,0],[0,0]],"v":[[-10.667,-22.625],[-10.479,22.188],[-3.667,22.625],[10.667,-22.625]],"c":true}},"nm":"Path 1","hd":false},{"ty":"gf","o":{"a":0,"k":100},"r":1,"bm":0,"g":{"p":3,"k":{"a":0,"k":[0,0.494,0.365,0.243,0.345,0.414,0.306,0.2,1,0.333,0.247,0.157,0,0,0.345,0.5,1,1]}},"s":{"a":0,"k":[-10.667,-0.625]},"e":{"a":0,"k":[-5.748,-0.625]},"t":1,"nm":"Gradient Fill 1","hd":false},{"ty":"tr","p":{"a":0,"k":[214.667,118.625]},"a":{"a":0,"k":[0,0]},"s":{"a":0,"k":[100,100]},"r":{"a":0,"k":0},"o":{"a":0,"k":100},"sk":{"a":0,"k":0},"sa":{"a":0,"k":0},"nm":"Transform"}],"nm":"Group 56","bm":0,"hd":false},{"ty":"gr","it":[{"ind":0,"ty":"sh","ks":{"a":0,"k":{"i":[[0,0],[0,0],[0,0],[0,0]],"o":[[0,0],[0,0],[0,0],[0,0]],"v":[[-58.625,180.25],[-39.125,180.25],[58.625,-177.375],[40.25,-180.25]],"c":true}},"nm":"Path 1","hd":false},{"ty":"fl","c":{"a":0,"k":[0.811764717102,0.635294139385,0.474509805441,1]},"o":{"a":0,"k":100},"r":1,"bm":0,"nm":"Fill 1","hd":false},{"ty":"tr","p":{"a":0,"k":[165.125,273.75]},"a":{"a":0,"k":[0,0]},"s":{"a":0,"k":[100,100]},"r":{"a":0,"k":0},"o":{"a":0,"k":100},"sk":{"a":0,"k":0},"sa":{"a":0,"k":0},"nm":"Transform"}],"nm":"Group 57","bm":0,"hd":false},{"ty":"gr","it":[{"ind":0,"ty":"sh","ks":{"a":0,"k":{"i":[[0,0],[0,0],[0,0],[0,0]],"o":[[0,0],[0,0],[0,0],[0,0]],"v":[[9.833,23.5],[-2.167,-28.5],[-9.833,-28.25],[3.583,28.5]],"c":false}},"nm":"Path 1","hd":false},{"ty":"st","c":{"a":0,"k":[0.266666680574,0.192156866193,0.1254902035,1]},"o":{"a":0,"k":100},"w":{"a":0,"k":6},"lc":2,"lj":2,"bm":0,"nm":"Stroke 1","hd":false},{"ty":"tr","p":{"a":0,"k":[316.667,113.75]},"a":{"a":0,"k":[0,0]},"s":{"a":0,"k":[100,100]},"r":{"a":0,"k":0},"o":{"a":0,"k":100},"sk":{"a":0,"k":0},"sa":{"a":0,"k":0},"nm":"Transform"}],"nm":"Group 58","bm":0,"hd":false},{"ty":"gr","it":[{"ind":0,"ty":"sh","ks":{"a":0,"k":{"i":[[0,0],[0,0],[0,0],[0,0]],"o":[[0,0],[0,0],[0,0],[0,0]],"v":[[-47.75,-183],[39.917,184.5],[47.75,184.5],[-40.917,-184.5]],"c":true}},"nm":"Path 1","hd":false},{"ty":"st","c":{"a":0,"k":[0.35686275363,0.247058823705,0.156862750649,1]},"o":{"a":0,"k":100},"w":{"a":0,"k":6},"lc":2,"lj":2,"bm":0,"nm":"Stroke 1","hd":false},{"ty":"tr","p":{"a":0,"k":[354.583,268.5]},"a":{"a":0,"k":[0,0]},"s":{"a":0,"k":[100,100]},"r":{"a":0,"k":0},"o":{"a":0,"k":100},"sk":{"a":0,"k":0},"sa":{"a":0,"k":0},"nm":"Transform"}],"nm":"Group 59","bm":0,"hd":false},{"ty":"gr","it":[{"ind":0,"ty":"sh","ks":{"a":0,"k":{"i":[[0,0],[0,0],[0,0],[0,0]],"o":[[0,0],[0,0],[0,0],[0,0]],"v":[[-51,-184.531],[38,184.531],[51,184.531],[-36.5,-181.719]],"c":true}},"nm":"Path 1","hd":false},{"ty":"st","c":{"a":0,"k":[0.509803950787,0.349019616842,0.239215686917,1]},"o":{"a":0,"k":100},"w":{"a":0,"k":6},"lc":2,"lj":2,"bm":0,"nm":"Stroke 1","hd":false},{"ty":"tr","p":{"a":0,"k":[364.5,268.469]},"a":{"a":0,"k":[0,0]},"s":{"a":0,"k":[100,100]},"r":{"a":0,"k":0},"o":{"a":0,"k":100},"sk":{"a":0,"k":0},"sa":{"a":0,"k":0},"nm":"Transform"}],"nm":"Group 60","bm":0,"hd":false},{"ty":"gr","it":[{"ind":0,"ty":"sh","ks":{"a":0,"k":{"i":[[0,0],[0,0],[0,0],[0,0]],"o":[[0,0],[0,0],[0,0],[0,0]],"v":[[7.167,17.25],[-0.167,-17.417],[-7.167,-16.917],[1,17.417]],"c":false}},"nm":"Path 1","hd":false},{"ty":"gf","o":{"a":0,"k":100},"r":1,"bm":0,"g":{"p":3,"k":{"a":0,"k":[0,0.494,0.365,0.243,0.345,0.414,0.306,0.2,1,0.333,0.247,0.157,0,0,0.345,0.5,1,1]}},"s":{"a":0,"k":[4.333,16.917]},"e":{"a":0,"k":[-1.667,-4.75]},"t":1,"nm":"Gradient Fill 1","hd":false},{"ty":"tr","p":{"a":0,"k":[316.667,112.083]},"a":{"a":0,"k":[0,0]},"s":{"a":0,"k":[100,100]},"r":{"a":0,"k":0},"o":{"a":0,"k":100},"sk":{"a":0,"k":0},"sa":{"a":0,"k":0},"nm":"Transform"}],"nm":"Group 61","bm":0,"hd":false},{"ty":"gr","it":[{"ind":0,"ty":"sh","ks":{"a":0,"k":{"i":[[0,0],[0,0],[0,0],[0,0]],"o":[[0,0],[0,0],[0,0],[0,0]],"v":[[-47.75,-183],[39.917,184.5],[47.75,184.5],[-40.917,-184.5]],"c":true}},"nm":"Path 1","hd":false},{"ty":"fl","c":{"a":0,"k":[0.494117647409,0.35686275363,0.192156866193,1]},"o":{"a":0,"k":100},"r":1,"bm":0,"nm":"Fill 1","hd":false},{"ty":"tr","p":{"a":0,"k":[354.583,268.5]},"a":{"a":0,"k":[0,0]},"s":{"a":0,"k":[100,100]},"r":{"a":0,"k":0},"o":{"a":0,"k":100},"sk":{"a":0,"k":0},"sa":{"a":0,"k":0},"nm":"Transform"}],"nm":"Group 62","bm":0,"hd":false},{"ty":"gr","it":[{"ind":0,"ty":"sh","ks":{"a":0,"k":{"i":[[0,0],[0,0],[0,0],[0,0]],"o":[[0,0],[0,0],[0,0],[0,0]],"v":[[-51.125,-184.469],[38.125,184.469],[51.125,184.469],[-36.375,-181.781]],"c":true}},"nm":"Path 1","hd":false},{"ty":"gf","o":{"a":0,"k":100},"r":1,"bm":0,"g":{"p":3,"k":{"a":0,"k":[0,1,0.776,0.573,0.345,0.98,0.747,0.504,1,0.961,0.718,0.435]}},"s":{"a":0,"k":[-6.375,1.469]},"e":{"a":0,"k":[4.625,-1.781]},"t":1,"nm":"Gradient Fill 1","hd":false},{"ty":"tr","p":{"a":0,"k":[364.375,268.531]},"a":{"a":0,"k":[0,0]},"s":{"a":0,"k":[100,100]},"r":{"a":0,"k":0},"o":{"a":0,"k":100},"sk":{"a":0,"k":0},"sa":{"a":0,"k":0},"nm":"Transform"}],"nm":"Group 63","bm":0,"hd":false},{"ty":"gr","it":[{"ind":0,"ty":"sh","ks":{"a":0,"k":{"i":[[0,0],[0,0],[0,0],[0,0]],"o":[[0,0],[0,0],[0,0],[0,0]],"v":[[45.5,3.333],[-41.833,10],[-45.5,-2],[41.167,-10]],"c":true}},"nm":"Path 1","hd":false},{"ty":"st","c":{"a":0,"k":[0.266666680574,0.192156866193,0.1254902035,1]},"o":{"a":0,"k":100},"w":{"a":0,"k":6},"lc":2,"lj":2,"bm":0,"nm":"Stroke 1","hd":false},{"ty":"tr","p":{"a":0,"k":[283.167,155]},"a":{"a":0,"k":[0,0]},"s":{"a":0,"k":[100,100]},"r":{"a":0,"k":0},"o":{"a":0,"k":100},"sk":{"a":0,"k":0},"sa":{"a":0,"k":0},"nm":"Transform"}],"nm":"Group 64","bm":0,"hd":false},{"ty":"gr","it":[{"ind":0,"ty":"sh","ks":{"a":0,"k":{"i":[[0,0],[0,0],[0,0],[0,0]],"o":[[0,0],[0,0],[0,0],[0,0]],"v":[[-43.333,5.333],[-34.167,2.333],[43,-5.333],[43.333,-2.667]],"c":false}},"nm":"Path 1","hd":false},{"ty":"st","c":{"a":0,"k":[0.35686275363,0.247058823705,0.156862750649,1]},"o":{"a":0,"k":100},"w":{"a":0,"k":6},"lc":2,"lj":2,"bm":0,"nm":"Stroke 1","hd":false},{"ty":"tr","p":{"a":0,"k":[281,147.667]},"a":{"a":0,"k":[0,0]},"s":{"a":0,"k":[100,100]},"r":{"a":0,"k":0},"o":{"a":0,"k":100},"sk":{"a":0,"k":0},"sa":{"a":0,"k":0},"nm":"Transform"}],"nm":"Group 65","bm":0,"hd":false},{"ty":"gr","it":[{"ind":0,"ty":"sh","ks":{"a":0,"k":{"i":[[0,0],[0,0],[0,0],[0,0]],"o":[[0,0],[0,0],[0,0],[0,0]],"v":[[45.5,3.333],[-41.833,10],[-45.5,-2],[41.167,-10]],"c":true}},"nm":"Path 1","hd":false},{"ty":"fl","c":{"a":0,"k":[0.376470595598,0.266666680574,0.180392161012,1]},"o":{"a":0,"k":100},"r":1,"bm":0,"nm":"Fill 1","hd":false},{"ty":"tr","p":{"a":0,"k":[283.167,155]},"a":{"a":0,"k":[0,0]},"s":{"a":0,"k":[100,100]},"r":{"a":0,"k":0},"o":{"a":0,"k":100},"sk":{"a":0,"k":0},"sa":{"a":0,"k":0},"nm":"Transform"}],"nm":"Group 66","bm":0,"hd":false},{"ty":"gr","it":[{"ind":0,"ty":"sh","ks":{"a":0,"k":{"i":[[0,0],[0,0],[0,0],[0,0]],"o":[[0,0],[0,0],[0,0],[0,0]],"v":[[45.5,3.833],[-41.833,9.5],[-45.5,-2.5],[41.167,-9.5]],"c":true}},"nm":"Path 1","hd":false},{"ty":"st","c":{"a":0,"k":[0.35686275363,0.247058823705,0.156862750649,1]},"o":{"a":0,"k":100},"w":{"a":0,"k":6},"lc":2,"lj":2,"bm":0,"nm":"Stroke 1","hd":false},{"ty":"tr","p":{"a":0,"k":[303.167,243.5]},"a":{"a":0,"k":[0,0]},"s":{"a":0,"k":[100,100]},"r":{"a":0,"k":0},"o":{"a":0,"k":100},"sk":{"a":0,"k":0},"sa":{"a":0,"k":0},"nm":"Transform"}],"nm":"Group 67","bm":0,"hd":false},{"ty":"gr","it":[{"ind":0,"ty":"sh","ks":{"a":0,"k":{"i":[[0,0],[0,0],[0,0],[0,0]],"o":[[0,0],[0,0],[0,0],[0,0]],"v":[[-43.333,5.333],[-34.167,1.333],[43,-5.333],[43.333,-1.667]],"c":false}},"nm":"Path 1","hd":false},{"ty":"st","c":{"a":0,"k":[0.35686275363,0.247058823705,0.156862750649,1]},"o":{"a":0,"k":100},"w":{"a":0,"k":6},"lc":2,"lj":2,"bm":0,"nm":"Stroke 1","hd":false},{"ty":"tr","p":{"a":0,"k":[301,235.667]},"a":{"a":0,"k":[0,0]},"s":{"a":0,"k":[100,100]},"r":{"a":0,"k":0},"o":{"a":0,"k":100},"sk":{"a":0,"k":0},"sa":{"a":0,"k":0},"nm":"Transform"}],"nm":"Group 68","bm":0,"hd":false},{"ty":"gr","it":[{"ind":0,"ty":"sh","ks":{"a":0,"k":{"i":[[0,0],[0,0],[0,0],[0,0]],"o":[[0,0],[0,0],[0,0],[0,0]],"v":[[45.5,3.833],[-41.833,9.5],[-45.5,-2.5],[41.167,-9.5]],"c":true}},"nm":"Path 1","hd":false},{"ty":"fl","c":{"a":0,"k":[0.470588237047,0.333333343267,0.207843139768,1]},"o":{"a":0,"k":100},"r":1,"bm":0,"nm":"Fill 1","hd":false},{"ty":"tr","p":{"a":0,"k":[303.167,243.5]},"a":{"a":0,"k":[0,0]},"s":{"a":0,"k":[100,100]},"r":{"a":0,"k":0},"o":{"a":0,"k":100},"sk":{"a":0,"k":0},"sa":{"a":0,"k":0},"nm":"Transform"}],"nm":"Group 69","bm":0,"hd":false},{"ty":"gr","it":[{"ind":0,"ty":"sh","ks":{"a":0,"k":{"i":[[0,0],[0,0],[0,0],[0,0]],"o":[[0,0],[0,0],[0,0],[0,0]],"v":[[45.5,5.833],[-41.833,7.5],[-45.5,-4.5],[41.167,-7.5]],"c":true}},"nm":"Path 1","hd":false},{"ty":"st","c":{"a":0,"k":[0.35686275363,0.247058823705,0.156862750649,1]},"o":{"a":0,"k":100},"w":{"a":0,"k":6},"lc":2,"lj":2,"bm":0,"nm":"Stroke 1","hd":false},{"ty":"tr","p":{"a":0,"k":[325.167,328.5]},"a":{"a":0,"k":[0,0]},"s":{"a":0,"k":[100,100]},"r":{"a":0,"k":0},"o":{"a":0,"k":100},"sk":{"a":0,"k":0},"sa":{"a":0,"k":0},"nm":"Transform"}],"nm":"Group 70","bm":0,"hd":false},{"ty":"gr","it":[{"ind":0,"ty":"sh","ks":{"a":0,"k":{"i":[[0,0],[0,0],[0,0],[0,0]],"o":[[0,0],[0,0],[0,0],[0,0]],"v":[[-43.333,3.833],[-34.167,-1.167],[43,-3.833],[43.333,0.833]],"c":false}},"nm":"Path 1","hd":false},{"ty":"st","c":{"a":0,"k":[0.35686275363,0.247058823705,0.156862750649,1]},"o":{"a":0,"k":100},"w":{"a":0,"k":6},"lc":2,"lj":2,"bm":0,"nm":"Stroke 1","hd":false},{"ty":"tr","p":{"a":0,"k":[323,320.167]},"a":{"a":0,"k":[0,0]},"s":{"a":0,"k":[100,100]},"r":{"a":0,"k":0},"o":{"a":0,"k":100},"sk":{"a":0,"k":0},"sa":{"a":0,"k":0},"nm":"Transform"}],"nm":"Group 71","bm":0,"hd":false},{"ty":"gr","it":[{"ind":0,"ty":"sh","ks":{"a":0,"k":{"i":[[0,0],[0,0],[0,0],[0,0]],"o":[[0,0],[0,0],[0,0],[0,0]],"v":[[45.5,5.833],[-41.833,7.5],[-45.5,-4.5],[41.167,-7.5]],"c":true}},"nm":"Path 1","hd":false},{"ty":"fl","c":{"a":0,"k":[0.470588237047,0.333333343267,0.207843139768,1]},"o":{"a":0,"k":100},"r":1,"bm":0,"nm":"Fill 1","hd":false},{"ty":"tr","p":{"a":0,"k":[325.167,328.5]},"a":{"a":0,"k":[0,0]},"s":{"a":0,"k":[100,100]},"r":{"a":0,"k":0},"o":{"a":0,"k":100},"sk":{"a":0,"k":0},"sa":{"a":0,"k":0},"nm":"Transform"}],"nm":"Group 72","bm":0,"hd":false},{"ty":"gr","it":[{"ind":0,"ty":"sh","ks":{"a":0,"k":{"i":[[0,0],[0,0],[0,0],[0,0]],"o":[[0,0],[0,0],[0,0],[0,0]],"v":[[45.5,6.333],[-41.833,7],[-45.5,-6],[41.167,-7]],"c":true}},"nm":"Path 1","hd":false},{"ty":"st","c":{"a":0,"k":[0.35686275363,0.247058823705,0.156862750649,1]},"o":{"a":0,"k":100},"w":{"a":0,"k":6},"lc":2,"lj":2,"bm":0,"nm":"Stroke 1","hd":false},{"ty":"tr","p":{"a":0,"k":[346.167,411]},"a":{"a":0,"k":[0,0]},"s":{"a":0,"k":[100,100]},"r":{"a":0,"k":0},"o":{"a":0,"k":100},"sk":{"a":0,"k":0},"sa":{"a":0,"k":0},"nm":"Transform"}],"nm":"Group 73","bm":0,"hd":false},{"ty":"gr","it":[{"ind":0,"ty":"sh","ks":{"a":0,"k":{"i":[[0,0],[0,0],[0,0],[0,0]],"o":[[0,0],[0,0],[0,0],[0,0]],"v":[[-43.333,3.333],[-34.167,-1.667],[43,-3.333],[43.333,2.333]],"c":false}},"nm":"Path 1","hd":false},{"ty":"st","c":{"a":0,"k":[0.35686275363,0.247058823705,0.156862750649,1]},"o":{"a":0,"k":100},"w":{"a":0,"k":6},"lc":2,"lj":2,"bm":0,"nm":"Stroke 1","hd":false},{"ty":"tr","p":{"a":0,"k":[344,401.667]},"a":{"a":0,"k":[0,0]},"s":{"a":0,"k":[100,100]},"r":{"a":0,"k":0},"o":{"a":0,"k":100},"sk":{"a":0,"k":0},"sa":{"a":0,"k":0},"nm":"Transform"}],"nm":"Group 74","bm":0,"hd":false},{"ty":"gr","it":[{"ind":0,"ty":"sh","ks":{"a":0,"k":{"i":[[0,0],[0,0],[0,0],[0,0]],"o":[[0,0],[0,0],[0,0],[0,0]],"v":[[45.5,6.333],[-41.833,7],[-45.5,-6],[41.167,-7]],"c":true}},"nm":"Path 1","hd":false},{"ty":"fl","c":{"a":0,"k":[0.505882382393,0.376470595598,0.254901975393,1]},"o":{"a":0,"k":100},"r":1,"bm":0,"nm":"Fill 1","hd":false},{"ty":"tr","p":{"a":0,"k":[346.167,411]},"a":{"a":0,"k":[0,0]},"s":{"a":0,"k":[100,100]},"r":{"a":0,"k":0},"o":{"a":0,"k":100},"sk":{"a":0,"k":0},"sa":{"a":0,"k":0},"nm":"Transform"}],"nm":"Group 75","bm":0,"hd":false},{"ty":"gr","it":[{"ind":0,"ty":"sh","ks":{"a":0,"k":{"i":[[0,0],[0,0],[0,0],[0,0]],"o":[[0,0],[0,0],[0,0],[0,0]],"v":[[13.083,39.375],[-6.25,-39.375],[-13.083,-37.875],[0.083,15.625]],"c":false}},"nm":"Path 1","hd":false},{"ty":"st","c":{"a":0,"k":[0.266666680574,0.192156866193,0.1254902035,1]},"o":{"a":0,"k":100},"w":{"a":0,"k":6},"lc":2,"lj":2,"bm":0,"nm":"Stroke 1","hd":false},{"ty":"tr","p":{"a":0,"k":[227.917,135.375]},"a":{"a":0,"k":[0,0]},"s":{"a":0,"k":[100,100]},"r":{"a":0,"k":0},"o":{"a":0,"k":100},"sk":{"a":0,"k":0},"sa":{"a":0,"k":0},"nm":"Transform"}],"nm":"Group 76","bm":0,"hd":false},{"ty":"gr","it":[{"ind":0,"ty":"sh","ks":{"a":0,"k":{"i":[[0,0],[0,0],[0,0],[0,0]],"o":[[0,0],[0,0],[0,0],[0,0]],"v":[[9.979,24.792],[-3.146,-27.5],[-9.979,-26],[3.188,27.5]],"c":false}},"nm":"Path 1","hd":false},{"ty":"gf","o":{"a":0,"k":100},"r":1,"bm":0,"g":{"p":3,"k":{"a":0,"k":[0,0.494,0.365,0.243,0.345,0.414,0.306,0.2,1,0.333,0.247,0.157,0,0,0.345,0.5,1,1]}},"s":{"a":0,"k":[6.188,26.5]},"e":{"a":0,"k":[-2.084,-8.039]},"t":1,"nm":"Gradient Fill 1","hd":false},{"ty":"tr","p":{"a":0,"k":[224.812,123.5]},"a":{"a":0,"k":[0,0]},"s":{"a":0,"k":[100,100]},"r":{"a":0,"k":0},"o":{"a":0,"k":100},"sk":{"a":0,"k":0},"sa":{"a":0,"k":0},"nm":"Transform"}],"nm":"Group 77","bm":0,"hd":false},{"ty":"gr","it":[{"ind":0,"ty":"sh","ks":{"a":0,"k":{"i":[[0,0],[0,0],[0,0]],"o":[[0,0],[0,0],[0,0]],"v":[[-12.667,-24.083],[1.167,-21.333],[12.667,24.083]],"c":false}},"nm":"Path 1","hd":false},{"ty":"st","c":{"a":0,"k":[0.266666680574,0.192156866193,0.1254902035,1]},"o":{"a":0,"k":100},"w":{"a":0,"k":6},"lc":2,"lj":2,"bm":0,"nm":"Stroke 1","hd":false},{"ty":"tr","p":{"a":0,"k":[234.833,120.083]},"a":{"a":0,"k":[0,0]},"s":{"a":0,"k":[100,100]},"r":{"a":0,"k":0},"o":{"a":0,"k":100},"sk":{"a":0,"k":0},"sa":{"a":0,"k":0},"nm":"Transform"}],"nm":"Group 78","bm":0,"hd":false},{"ty":"gr","it":[{"ind":0,"ty":"sh","ks":{"a":0,"k":{"i":[[0,0],[0,0],[0,0],[0,0]],"o":[[0,0],[0,0],[0,0],[0,0]],"v":[[-47.75,-177],[39.917,178.5],[47.75,178.5],[-40.917,-178.5]],"c":true}},"nm":"Path 1","hd":false},{"ty":"st","c":{"a":0,"k":[0.35686275363,0.247058823705,0.156862750649,1]},"o":{"a":0,"k":100},"w":{"a":0,"k":6},"lc":2,"lj":2,"bm":0,"nm":"Stroke 1","hd":false},{"ty":"tr","p":{"a":0,"k":[262.583,274.5]},"a":{"a":0,"k":[0,0]},"s":{"a":0,"k":[100,100]},"r":{"a":0,"k":0},"o":{"a":0,"k":100},"sk":{"a":0,"k":0},"sa":{"a":0,"k":0},"nm":"Transform"}],"nm":"Group 79","bm":0,"hd":false},{"ty":"gr","it":[{"ind":0,"ty":"sh","ks":{"a":0,"k":{"i":[[0,0],[0,0],[0,0],[0,0]],"o":[[0,0],[0,0],[0,0],[0,0]],"v":[[-47.75,-177],[39.917,178.5],[47.75,178.5],[-40.917,-178.5]],"c":true}},"nm":"Path 1","hd":false},{"ty":"fl","c":{"a":0,"k":[0.486274510622,0.384313732386,0.254901975393,1]},"o":{"a":0,"k":100},"r":1,"bm":0,"nm":"Fill 1","hd":false},{"ty":"tr","p":{"a":0,"k":[262.583,274.5]},"a":{"a":0,"k":[0,0]},"s":{"a":0,"k":[100,100]},"r":{"a":0,"k":0},"o":{"a":0,"k":100},"sk":{"a":0,"k":0},"sa":{"a":0,"k":0},"nm":"Transform"}],"nm":"Group 80","bm":0,"hd":false},{"ty":"gr","it":[{"ind":0,"ty":"sh","ks":{"a":0,"k":{"i":[[0,0],[0,0],[0,0],[0,0]],"o":[[0,0],[0,0],[0,0],[0,0]],"v":[[-51.125,-178.469],[38.125,178.469],[51.125,178.469],[-36.375,-175.781]],"c":true}},"nm":"Path 1","hd":false},{"ty":"st","c":{"a":0,"k":[0.509803950787,0.349019616842,0.239215686917,1]},"o":{"a":0,"k":100},"w":{"a":0,"k":6},"lc":2,"lj":2,"bm":0,"nm":"Stroke 1","hd":false},{"ty":"tr","p":{"a":0,"k":[272.375,274.531]},"a":{"a":0,"k":[0,0]},"s":{"a":0,"k":[100,100]},"r":{"a":0,"k":0},"o":{"a":0,"k":100},"sk":{"a":0,"k":0},"sa":{"a":0,"k":0},"nm":"Transform"}],"nm":"Group 81","bm":0,"hd":false},{"ty":"gr","it":[{"ind":0,"ty":"sh","ks":{"a":0,"k":{"i":[[0,0],[0,0],[0,0],[0,0],[0,0]],"o":[[0,0],[0,0],[0,0],[0,0],[0,0]],"v":[[6.625,-17.25],[6.125,18.5],[1,18.5],[-6.625,-18.5],[6.625,-17.25]],"c":false}},"nm":"Path 1","hd":false},{"ty":"gf","o":{"a":0,"k":100},"r":1,"bm":0,"g":{"p":3,"k":{"a":0,"k":[0,0.494,0.365,0.243,0.345,0.494,0.365,0.243,1,0.494,0.365,0.243,0,0,0.345,0.5,1,1]}},"s":{"a":0,"k":[5.375,-0.75]},"e":{"a":0,"k":[2.593,-0.75]},"t":1,"nm":"Gradient Fill 1","hd":false},{"ty":"tr","p":{"a":0,"k":[308.625,434.75]},"a":{"a":0,"k":[0,0]},"s":{"a":0,"k":[100,100]},"r":{"a":0,"k":0},"o":{"a":0,"k":100},"sk":{"a":0,"k":0},"sa":{"a":0,"k":0},"nm":"Transform"}],"nm":"Group 82","bm":0,"hd":false},{"ty":"gr","it":[{"ind":0,"ty":"sh","ks":{"a":0,"k":{"i":[[0,0],[0,0],[0,0],[0,0]],"o":[[0,0],[0,0],[0,0],[0,0]],"v":[[4.25,-32],[9,33.25],[-9,-33.25],[4.25,-32]],"c":false}},"nm":"Path 1","hd":false},{"ty":"gf","o":{"a":0,"k":100},"r":1,"bm":0,"g":{"p":3,"k":{"a":0,"k":[0,0.494,0.365,0.243,0.345,0.494,0.365,0.243,1,0.494,0.365,0.243,0,0,0.345,0.5,1,1]}},"s":{"a":0,"k":[6.5,-0.5]},"e":{"a":0,"k":[2.721,-0.5]},"t":1,"nm":"Gradient Fill 1","hd":false},{"ty":"tr","p":{"a":0,"k":[247.5,197.5]},"a":{"a":0,"k":[0,0]},"s":{"a":0,"k":[100,100]},"r":{"a":0,"k":0},"o":{"a":0,"k":100},"sk":{"a":0,"k":0},"sa":{"a":0,"k":0},"nm":"Transform"}],"nm":"Group 83","bm":0,"hd":false},{"ty":"gr","it":[{"ind":0,"ty":"sh","ks":{"a":0,"k":{"i":[[0,0],[0,0],[0,0],[0,0]],"o":[[0,0],[0,0],[0,0],[0,0]],"v":[[4.25,-32],[9,33.25],[-9,-33.25],[4.25,-32]],"c":false}},"nm":"Path 1","hd":false},{"ty":"gf","o":{"a":0,"k":100},"r":1,"bm":0,"g":{"p":3,"k":{"a":0,"k":[0,0.494,0.365,0.243,0.345,0.494,0.365,0.243,1,0.494,0.365,0.243,0,0,0.345,0.5,1,1]}},"s":{"a":0,"k":[7.25,-0.75]},"e":{"a":0,"k":[3.471,-0.75]},"t":1,"nm":"Gradient Fill 1","hd":false},{"ty":"tr","p":{"a":0,"k":[269.75,284.75]},"a":{"a":0,"k":[0,0]},"s":{"a":0,"k":[100,100]},"r":{"a":0,"k":0},"o":{"a":0,"k":100},"sk":{"a":0,"k":0},"sa":{"a":0,"k":0},"nm":"Transform"}],"nm":"Group 84","bm":0,"hd":false},{"ty":"gr","it":[{"ind":0,"ty":"sh","ks":{"a":0,"k":{"i":[[0,0],[0,0],[0,0],[0,0]],"o":[[0,0],[0,0],[0,0],[0,0]],"v":[[4.75,-31.125],[8.5,32.375],[-8.5,-32.375],[4.75,-31.125]],"c":false}},"nm":"Path 1","hd":false},{"ty":"gf","o":{"a":0,"k":100},"r":1,"bm":0,"g":{"p":3,"k":{"a":0,"k":[0,0.494,0.365,0.243,0.345,0.494,0.365,0.243,1,0.494,0.365,0.243,0,0,0.345,0.5,1,1]}},"s":{"a":0,"k":[7,-0.625]},"e":{"a":0,"k":[3.431,-0.625]},"t":1,"nm":"Gradient Fill 1","hd":false},{"ty":"tr","p":{"a":0,"k":[290,366.625]},"a":{"a":0,"k":[0,0]},"s":{"a":0,"k":[100,100]},"r":{"a":0,"k":0},"o":{"a":0,"k":100},"sk":{"a":0,"k":0},"sa":{"a":0,"k":0},"nm":"Transform"}],"nm":"Group 85","bm":0,"hd":false},{"ty":"gr","it":[{"ind":0,"ty":"sh","ks":{"a":0,"k":{"i":[[0,0],[0,0],[0,0],[0,0]],"o":[[0,0],[0,0],[0,0],[0,0]],"v":[[0.917,29.25],[-13.417,-29.25],[0.917,-26.5],[13.417,24.75]],"c":false}},"nm":"Path 1","hd":false},{"ty":"gf","o":{"a":0,"k":100},"r":1,"bm":0,"g":{"p":3,"k":{"a":0,"k":[0,0.494,0.365,0.243,0.267,0.414,0.306,0.2,1,0.333,0.247,0.157,0,0,0.267,0.5,1,1]}},"s":{"a":0,"k":[11.917,43.75]},"e":{"a":0,"k":[-6.083,-26.25]},"t":1,"nm":"Gradient Fill 1","hd":false},{"ty":"tr","p":{"a":0,"k":[235.083,125.25]},"a":{"a":0,"k":[0,0]},"s":{"a":0,"k":[100,100]},"r":{"a":0,"k":0},"o":{"a":0,"k":100},"sk":{"a":0,"k":0},"sa":{"a":0,"k":0},"nm":"Transform"}],"nm":"Group 86","bm":0,"hd":false},{"ty":"gr","it":[{"ind":0,"ty":"sh","ks":{"a":0,"k":{"i":[[0,0],[0,0],[0,0],[0,0]],"o":[[0,0],[0,0],[0,0],[0,0]],"v":[[-10.75,-12.625],[-2.75,18.875],[10.75,16.875],[1.75,-18.875]],"c":false}},"nm":"Path 1","hd":false},{"ty":"gf","o":{"a":0,"k":100},"r":1,"bm":0,"g":{"p":3,"k":{"a":0,"k":[0,0.494,0.365,0.243,0.345,0.494,0.365,0.243,1,0.494,0.365,0.243,0,0,0.345,0.5,1,1]}},"s":{"a":0,"k":[-5,-16.375]},"e":{"a":0,"k":[4.5,19.625]},"t":1,"nm":"Gradient Fill 1","hd":false},{"ty":"tr","p":{"a":0,"k":[264,231.375]},"a":{"a":0,"k":[0,0]},"s":{"a":0,"k":[100,100]},"r":{"a":0,"k":0},"o":{"a":0,"k":100},"sk":{"a":0,"k":0},"sa":{"a":0,"k":0},"nm":"Transform"}],"nm":"Group 87","bm":0,"hd":false},{"ty":"gr","it":[{"ind":0,"ty":"sh","ks":{"a":0,"k":{"i":[[0,0],[0,0],[0,0],[0,0]],"o":[[0,0],[0,0],[0,0],[0,0]],"v":[[-10.75,-12.625],[-2.75,18.875],[10.75,16.875],[1.75,-18.875]],"c":false}},"nm":"Path 1","hd":false},{"ty":"gf","o":{"a":0,"k":100},"r":1,"bm":0,"g":{"p":3,"k":{"a":0,"k":[0,0.494,0.365,0.243,0.345,0.494,0.365,0.243,1,0.494,0.365,0.243,0,0,0.345,0.5,1,1]}},"s":{"a":0,"k":[-5,-15.875]},"e":{"a":0,"k":[4.5,20.125]},"t":1,"nm":"Gradient Fill 1","hd":false},{"ty":"tr","p":{"a":0,"k":[283,312.875]},"a":{"a":0,"k":[0,0]},"s":{"a":0,"k":[100,100]},"r":{"a":0,"k":0},"o":{"a":0,"k":100},"sk":{"a":0,"k":0},"sa":{"a":0,"k":0},"nm":"Transform"}],"nm":"Group 88","bm":0,"hd":false},{"ty":"gr","it":[{"ind":0,"ty":"sh","ks":{"a":0,"k":{"i":[[0,0],[0,0],[0,0],[0,0]],"o":[[0,0],[0,0],[0,0],[0,0]],"v":[[-16.625,-35.812],[3.25,40.312],[16.625,40.062],[-1.625,-40.312]],"c":false}},"nm":"Path 1","hd":false},{"ty":"gf","o":{"a":0,"k":100},"r":1,"bm":0,"g":{"p":5,"k":{"a":0,"k":[0,0.494,0.365,0.243,0.223,0.494,0.365,0.243,0.514,0.494,0.365,0.243,0.754,0.494,0.365,0.243,1,0.494,0.365,0.243,0,0,0.223,0.5,0.514,1,0.754,0.528,1,0.057]}},"s":{"a":0,"k":[10.375,36.688]},"e":{"a":0,"k":[-8.718,-34.038]},"t":1,"nm":"Gradient Fill 1","hd":false},{"ty":"tr","p":{"a":0,"k":[305.625,411.312]},"a":{"a":0,"k":[0,0]},"s":{"a":0,"k":[100,100]},"r":{"a":0,"k":0},"o":{"a":0,"k":100},"sk":{"a":0,"k":0},"sa":{"a":0,"k":0},"nm":"Transform"}],"nm":"Group 89","bm":0,"hd":false},{"ty":"gr","it":[{"ind":0,"ty":"sh","ks":{"a":0,"k":{"i":[[0,0],[0,0],[0,0],[0,0]],"o":[[0,0],[0,0],[0,0],[0,0]],"v":[[-51.125,-178.469],[38.125,178.469],[51.125,178.469],[-36.375,-175.781]],"c":true}},"nm":"Path 1","hd":false},{"ty":"fl","c":{"a":0,"k":[0.890196084976,0.674509823322,0.466666668653,1]},"o":{"a":0,"k":100},"r":1,"bm":0,"nm":"Fill 1","hd":false},{"ty":"tr","p":{"a":0,"k":[272.375,274.531]},"a":{"a":0,"k":[0,0]},"s":{"a":0,"k":[100,100]},"r":{"a":0,"k":0},"o":{"a":0,"k":100},"sk":{"a":0,"k":0},"sa":{"a":0,"k":0},"nm":"Transform"}],"nm":"Group 90","bm":0,"hd":false},{"ty":"gr","it":[{"ind":0,"ty":"sh","ks":{"a":0,"k":{"i":[[0,0],[0,0],[0,0],[0,0],[0,0]],"o":[[0,0],[0,0],[0,0],[0,0],[0,0]],"v":[[-75.083,6.875],[-30.417,11.125],[75.083,-4.125],[34.417,-11.125],[-75.083,6.875]],"c":false}},"nm":"Path 1","hd":false},{"ty":"st","c":{"a":0,"k":[0.266666680574,0.192156866193,0.1254902035,1]},"o":{"a":0,"k":100},"w":{"a":0,"k":6},"lc":2,"lj":2,"bm":0,"nm":"Stroke 1","hd":false},{"ty":"tr","p":{"a":0,"k":[262.667,87.125]},"a":{"a":0,"k":[0,0]},"s":{"a":0,"k":[100,100]},"r":{"a":0,"k":0},"o":{"a":0,"k":100},"sk":{"a":0,"k":0},"sa":{"a":0,"k":0},"nm":"Transform"}],"nm":"Group 91","bm":0,"hd":false},{"ty":"gr","it":[{"ind":0,"ty":"sh","ks":{"a":0,"k":{"i":[[0,0],[0,0],[0,0],[0,0],[0,0]],"o":[[0,0],[0,0],[0,0],[0,0],[0,0]],"v":[[-75.083,6.875],[-30.417,11.125],[75.083,-4.125],[34.417,-11.125],[-75.083,6.875]],"c":false}},"nm":"Path 1","hd":false},{"ty":"fl","c":{"a":0,"k":[0.313725501299,0.227450981736,0.145098045468,1]},"o":{"a":0,"k":100},"r":1,"bm":0,"nm":"Fill 1","hd":false},{"ty":"tr","p":{"a":0,"k":[262.667,87.125]},"a":{"a":0,"k":[0,0]},"s":{"a":0,"k":[100,100]},"r":{"a":0,"k":0},"o":{"a":0,"k":100},"sk":{"a":0,"k":0},"sa":{"a":0,"k":0},"nm":"Transform"}],"nm":"Group 92","bm":0,"hd":false},{"ty":"gr","it":[{"ind":0,"ty":"sh","ks":{"a":0,"k":{"i":[[-0.167,-1.167],[0,0],[-0.167,1.667],[0,0]],"o":[[0.167,1.167],[0,0],[0.167,-1.667],[0,0]],"v":[[56,2.853],[-0.5,4.353],[-56,-4.147],[-0.667,3.186]],"c":true}},"nm":"Path 1","hd":false},{"ty":"st","c":{"a":0,"k":[0.415686279535,0.40000000596,0.388235300779,1]},"o":{"a":0,"k":100},"w":{"a":0,"k":8},"lc":2,"lj":2,"bm":0,"nm":"Stroke 1","hd":false},{"ty":"tr","p":{"a":0,"k":[220,286.814]},"a":{"a":0,"k":[0,0]},"s":{"a":0,"k":[100,100]},"r":{"a":0,"k":0},"o":{"a":0,"k":100},"sk":{"a":0,"k":0},"sa":{"a":0,"k":0},"nm":"Transform"}],"nm":"Group 93","bm":0,"hd":false}],"ip":0,"op":1,"st":0,"bm":0}]}